{"ぬりかくす":1,"ぬんちゃく":1,"ぬるぽん":1,"ぬくさり":1,"ぬるはち":1,"ぬきはなつ":1,"ぬのはば":1,"ぬーどすたじお":1,"ぬいばり":1,"ぬいはく":1,"ぬえぬえ":1,"ぬーぶらー":1,"ぬくいきたまち":1,"ぬこる":1,"ぬくぬくそくほう":1,"ぬーぶ":1,"ぬでじまじろう":1,"ぬて":1,"ぬいと":1,"ぬまづえき":1,"ぬちまーす":1,"ぬしやみくずのろーぶ":1,"ぬゅーだ":1,"ぬまづしえばらちょう":1,"ぬまっき":1,"ぬきとる":1,"ぬきつぬかれつ":1,"ぬのおしとみとりなるどみのかみ":1,"ぬけべんてん":1,"ぬすっとこんじょう":1,"ぬかる":1,"ぬるこむ":1,"ぬすみあし":1,"ぬけだす":1,"ぬくもりぴー":1,"ぬかこーら":1,"ぬまたちょう":1,"ぬぅぼ":1,"ぬりえ":1,"ぬのびきはーぶえん":1,"ぬのじ":1,"ぬかか":1,"ぬまた":1,"ぬわじま":1,"ぬくすわるぷるぎす":1,"ぬでじま":1,"ぬけまいり":1,"ぬすみぎき":1,"ぬりこめる":1,"ぬこのひと":1,"ぬかおとまるまち":1,"ぬのしひめのみこと":1,"ぬぎそろえる":1,"ぬーちゃやまち":1,"ぬきてん":1,"ぬのせえき":1,"ぬで":1,"ぬぅ":1,"ぬまたにかすみ":1,"ぬのびきごほんまつだむ":1,"ぬしはかれーずき":1,"ぬまづし":1,"ぬくべからざる":1,"ぬーぶれら":1,"ぬた":1,"ぬお":1,"ぬいとり":1,"ぬいもの":1,"ぬこやすなまほうそうぬし":1,"ぬまづじょうほく":1,"ぬけさくせんまいふでならし":1,"ぬいぐるみ":1,"ぬーら":1,"ぬき":1,"ぬまわに":1,"ぬかみそ":1,"ぬーこ":1,"ぬれぎぬをはらす":1,"ぬけないえーぶいじょゆう":1,"ぬくれおしど":1,"ぬーばす":1,"ぬまち":1,"ぬるぬるどうが":1,"ぬっこ":1,"ぬゃかな":1,"ぬーどもでる":1,"ぬらりくお":1,"ぬれてにあわ":1,"ぬすみわらい":1,"ぬきうち":1,"ぬかばえ":1,"ぬーおろけん":1,"ぬのしだ":1,"ぬまねこ":1,"ぬかたのおおなかつひこのおうじ":1,"ぬぐう":1,"ぬきいと":1,"ぬまづしんようきんこ":1,"ぬーどからー":1,"ぬしゃみ":1,"ぬくめざけ":1,"ぬじゃべす":1,"ぬひこっか":1,"ぬしのどくじのふぃるたーがかかっています":1,"ぬっちょ":1,"ぬーゔぇるふらんす":1,"ぬーどるす":1,"ぬきげ":1,"ぬりかためる":1,"ぬすとたけだけしい":1,"ぬく":1,"ぬしはいませんじょうにいってるんだ":1,"ぬまみなみまち":1,"ぬびあこねくしょん":1,"ぬっぽりんこ":1,"ぬしろぐ":1,"ぬーじー":1,"ぬまたさとし":1,"ぬっきー":1,"ぬかどこ":1,"ぬーおろ":1,"ぬーぼぬーど":1,"ぬるぬるうごく":1,"ぬぬるぽ":1,"ぬっころ":1,"ぬじょーるほう":1,"ぬめりささたけ":1,"ぬきに":1,"ぬこはむ":1,"ぬきんでる":1,"ぬまよしのぶ":1,"ぬばたまの":1,"ぬえびーむ":1,"ぬらまご":1,"ぬりもの":1,"ぬきさし":1,"ぬれぎぬ":1,"ぬるがわおんせん":1,"ぬこぷらすしりーず":1,"ぬきなすうおう":1,"ぬすみみ":1,"ぬふぅ":1,"ぬすっとぶんか":1,"ぬまざわたつお":1,"ぬま":1,"ぬわぃ":1,"ぬきさきじんじゃ":1,"ぬまざわおんせん":1,"ぬかがは":1,"ぬくもる":1,"ぬすびと":1,"ぬれごと":1,"ぬりがさ":1,"ぬむじかえーしーてん":1,"ぬぴずわり":1,"ぬるすけ":1,"ぬこじる":1,"ぬるもでむけーぶる":1,"ぬこらじぬくもりがこいしくなるらじお":1,"ぬさをたてまつる":1,"ぬーとりあ":1,"ぬこそくほう":1,"ぬまたえき":1,"ぬまくらえりこ":1,"ぬまくろー":1,"ぬすっとたけだけしい":1,"ぬんぬんぼっち":1,"ぬるぽっていっていちじかんいないにがってされなかったらおうじゃ":1,"ぬーどさつえいかい":1,"ぬいあげ":1,"ぬるでれ":1,"ぬのさらし":1,"ぬくぬくまーじゃん":1,"ぬまくまはんとう":1,"ぬすっとねこ":1,"ぬるがた":1,"ぬえのりんかく":1,"ぬーべるしのわ":1,"ぬまくらくんぶるーばっくしりーず":1,"ぬきどる":1,"ぬかづけのうた":1,"ぬなっつ":1,"ぬっしぃ":1,"ぬぁなさん":1,"ぬこす":1,"ぬれたおる":1,"ぬすみ":1,"ぬりかえる":1,"ぬりくん":1,"ぬまのみつよし":1,"ぬけめない":1,"ぬまのはた":1,"ぬくりえき":1,"ぬくしなちょう":1,"ぬかだきたごう":1,"ぬれがみだいみょうじん":1,"ぬなわ":1,"ぬいもん":1,"ぬのひき":1,"ぬりかべ":1,"ぬこですの":1,"ぬかじろゆう":1,"ぬちぐすい":1,"ぬただ":1,"ぬけめがない":1,"ぬりいた":1,"ぬってもいいのよ":1,"ぬきたつと":1,"ぬしでれ":1,"ぬぷり":1,"ぬけぼー":1,"ぬすみぐい":1,"ぬればいろ":1,"ぬいめ":1,"ぬるぽ":1,"ぬさ":1,"ぬめいる":1,"ぬきにして":1,"ぬっぺらぼう":1,"ぬかもふちえぶくろ":1,"ぬくれおちど":1,"ぬめかわ":1,"ぬきでる":1,"ぬまたまち":1,"ぬこでぃーじぇーさん":1,"ぬこえくすぺりえんす":1,"ぬめるごん":1,"ぬがー":1,"ぬすっと":1,"ぬぐいさる":1,"ぬっぱらい":1,"ぬの":1,"ぬすまれたてがみ":1,"ぬのぶくろ":1,"ぬかしんぼ":1,"ぬきみ":1,"ぬかた":1,"ぬかよろこび":1,"ぬたひがしちょう":1,"ぬらりくらり":1,"ぬこにゅん":1,"ぬあくしょっと":1,"ぬたうなぎぞく":1,"ぬきうちちょうさ":1,"ぬわーーっっ":1,"ぬきやよいがおか":1,"ぬくあろふぁ":1,"ぬるぼう":1,"ぬるぬるじーべん":1,"ぬいつける":1,"ぬるい":1,"ぬしこめがびょうきしりーず":1,"ぬこわっぱ":1,"ぬりしりょう":1,"ぬかたべみなみちょう":1,"ぬーん":1,"ぬれてぃーしゃつこんてすと":1,"ぬこぱぱ":1,"ぬけんじょうげーむ":1,"ぬのべたかのり":1,"ぬるどぅん":1,"ぬきだす":1,"ぬりたて":1,"ぬりつける":1,"ぬかたべてらまち":1,"ぬめろん":1,"ぬるまゆ":1,"ぬーすけせんぱい":1,"ぬけげ":1,"ぬるてかぴー":1,"ぬのおむつ":1,"ぬこぬこぬこぬこ":1,"ぬーくれあ":1,"ぬるむ":1,"ぬこたろす":1,"ぬけめのない":1,"ぬるぬるおとこ":1,"ぬなかわひめ":1,"ぬるりすと":1,"ぬけみち":1,"ぬのはら":1,"ぬくもり":1,"ぬしはうわきもの":1,"ぬのいちえき":1,"ぬくぬく":1,"ぬかづかきゅうり":1,"ぬいぐるまー":1,"ぬまづこうしんかいすいぞくかん":1,"ぬひずいぼほう":1,"ぬげば":1,"ぬくれおそーむ":1,"ぬけさく":1,"ぬまづしょう":1,"ぬわー":1,"ぬかづけ":1,"ぬからぬかお":1,"ぬかたべきたまち":1,"ぬかるむ":1,"ぬるもじ":1,"ぬーんのひと":1,"ぬのびきぐりーんすたじあむ":1,"ぬきさる":1,"ぬのむらかずお":1,"ぬめんた":1,"ぬのきれ":1,"ぬーぴー":1,"ぬるゆおんせん":1,"ぬかじゅうたくまええき":1,"ぬこかぜ":1,"ぬえるぞく":1,"ぬかみそづけ":1,"ぬぎたいだけ":1,"ぬくぬくおれんじ":1,"ぬのうらつばさ":1,"ぬなきいりびめのみこと":1,"ぬーでぃすとびーち":1,"ぬーぼー":1,"ぬりつぶす":1,"ぬけめ":1,"ぬきげとーなめんと":1,"ぬえぼばし":1,"ぬーべるふらんす":1,"ぬゔー":1,"ぬかだいわお":1,"ぬれねずみ":1,"ぬしさま":1,"ぬっと":1,"ぬりで":1,"ぬしま":1,"ぬまっち":1,"ぬのめ":1,"ぬーでぃー":1,"ぬくいだむ":1,"ぬえりつき":1,"ぬのこ":1,"ぬのなぷきん":1,"ぬらり":1,"ぬぎぬぎ":1,"ぬくれあーぜ":1,"ぬーどる":1,"ぬけおちる":1,"ぬまづこうせん":1,"ぬくもりてぃ":1,"ぬまじりさやか":1,"ぬこびっちるき":1,"ぬかづく":1,"ぬっち":1,"ぬい":1,"ぬのけいいちろう":1,"ぬいぐろみ":1,"ぬかがみ":1,"ぬらりひょん":1,"ぬのぞうり":1,"ぬいてますよあざぜるさん":1,"ぬるぬるおうじ":1,"ぬどん":1,"ぬこまんま":1,"ぬんじゃ":1,"ぬまくまぐん":1,"ぬいだらとぅるーで":1,"ぬーでぃーからー":1,"ぬんど":1,"ぬなぶとじゅんしゅう":1,"ぬぽお":1,"ぬーゔぉー":1,"ぬいとる":1,"ぬまたとしや":1,"ぬしがんばりますわたしいがいが":1,"ぬすんでいきましたしりーず":1,"ぬいのつかさ":1,"ぬまたぐん":1,"ぬめりすぎたけもどき":1,"ぬかるみ":1,"ぬいしろをわる":1,"ぬすみとる":1,"ぬかずき":1,"ぬーかすーはー":1,"ぬーど":1,"ぬすみみる":1,"ぬのむらこういち":1,"ぬこぬこひめ":1,"ぬーでぃすと":1,"ぬれがみ":1,"ぬん":1,"ぬぅん":1,"ぬけにん":1,"ぬすっとがり":1,"ぬっぽん":1,"ぬめりいぐち":1,"ぬばっく":1,"ぬびあ":1,"ぬたうつ":1,"ぬげる":1,"ぬれせんべい":1,"ぬすみだす":1,"ぬきで":1,"ぬかだ":1,"ぬいこむ":1,"ぬしのこいびとはこあら":1,"ぬことら":1,"ぬふす":1,"ぬーくですこああたっく":1,"ぬすっとこうざ":1,"ぬかがあきお":1,"ぬーどるくえすと":1,"ぬくしな":1,"ぬてら":1,"ぬるふぃーるど":1,"ぬかみちゅう":1,"ぬまおひろこ":1,"ぬこもやしぴー":1,"ぬくめる":1,"ぬるぱたん":1,"ぬのぎれ":1,"ぬきしげと":1,"ぬらんどほうどうかん":1,"ぬりぐすり":1,"ぬるてま":1,"ぬーしゃてる":1,"ぬけかわる":1,"ぬまむつ":1,"ぬこむら":1,"ぬれごとし":1,"ぬかるみみち":1,"ぬくしなばいぱす":1,"ぬりばし":1,"ぬいどり":1,"ぬまがれい":1,"ぬまたじゅん":1,"ぬこにゃん":1,"ぬしのめいげんもうかえるっ":1,"ぬかがちょうかん":1,"ぬきあし":1,"ぬえぼれおんしゅう":1,"ぬえてき":1,"ぬまたゆういちろう":1,"ぬえざきぽんたま":1,"ぬこしゃ":1,"ぬるぽいんたえくせぷしょん":1,"ぬきとおす":1,"ぬえら":1,"ぬがす":1,"ぬばたま":1,"ぬーでぃからー":1,"ぬきとりけんさ":1,"ぬひ":1,"ぬすばうむ":1,"ぬまづあるぷす":1,"ぬきこうばい":1,"ぬまたすずこ":1,"ぬみでぃあ":1,"ぬんすけ":1,"ぬし":1,"ぬれいえふ":1,"ぬまちん":1,"ぬまおやき":1,"ぬぎちゃ":1,"ぬけうら":1,"ぬいぐるみさんとのくらしかた":1,"ぬくみ":1,"ぬぐ":1,"ぬるばいと":1,"ぬたにしちょう":1,"ぬれきちむお":1,"ぬるのしん":1,"ぬらりひょんのまご":1,"ぬきわざ":1,"ぬのばり":1,"ぬこあるく":1,"ぬえどり":1,"ぬのざきえき":1,"ぬぬ":1,"ぬれてぃっしゅ":1,"ぬこっこ":1,"ぬきうちけんさ":1,"ぬこ":1,"ぬいてみな":1,"ぬりこ":1,"ぬいあわせる":1,"ぬー":1,"ぬるたろうなまほうそうぬし":1,"ぬまのきょうこ":1,"ぬかだひさのり":1,"ぬまじりこうざん":1,"ぬすんでいきました":1,"ぬすびとにもさんぶのり":1,"ぬくた":1,"ぬのびきまるじけん":1,"ぬまたげんき":1,"ぬけぬけ":1,"ぬすめないほうせき":1,"ぬりて":1,"ぬびら":1,"ぬーゔぇるきゅいじーぬ":1,"ぬかたえき":1,"ぬれるっ":1,"ぬーゔぁー":1,"ぬるで":1,"ぬーらぼ":1,"ぬかたぐん":1,"ぬしぬし":1,"ぬままんぐーす":1,"ぬけでる":1,"ぬこかん":1,"ぬりごめ":1,"ぬりべのきみたり":1,"ぬまたせいや":1,"ぬくい":1,"ぬれせい":1,"ぬめる":1,"ぬーゔぉーろまん":1,"ぬのきりえ":1,"ぬるまっくす":1,"ぬまぶくろえき":1,"ぬすまれたくちびる":1,"ぬかざわ":1,"ぬおー":1,"ぬるこむあーかいぶす":1,"ぬまだ":1,"ぬりげた":1,"ぬれんざ":1,"ぬきましたわー":1,"ぬんぽくらふと":1,"ぬくいちょう":1,"ぬーべー":1,"ぬれそぼつ":1,"ぬまんしあ":1,"ぬっけ":1,"ぬかご":1,"ぬこぴー":1,"ぬころ":1,"ぬんっ":1,"ぬーゔぉれこると":1,"ぬひせい":1,"ぬたうなぎ":1,"ぬわんつかれたもん":1,"ぬーべるばーぐ":1,"ぬでれば":1,"ぬきはなす":1,"ぬさどぅあ":1,"ぬかずく":1,"ぬーべるきゅいじーぬ":1,"ぬらす":1,"ぬーべるゔぁーぐ":1,"ぬーゔぇるゔぁーぐ":1,"ぬかむらまゆ":1,"ぬーくりあ":1,"ぬままんぐーすぞく":1,"ぬくり":1,"ぬりなおし":1,"ぬかつく":1,"ぬきぞめ":1,"ぬかさんま":1,"ぬりぼとけのうたげ":1,"ぬまづひがしこうこう":1,"ぬーるとう":1,"ぬたちょう":1,"ぬーそく":1,"ぬけーく":1,"ぬーぼーろまん":1,"ぬかす":1,"ぬるもでむ":1,"ぬたはらふみお":1,"ぬりん":1,"ぬのびきだい":1,"ぬこぬこどうが":1,"ぬりわける":1,"ぬるぽほうそうきょく":1,"ぬーしゃてるしゅう":1,"ぬこひめあっとさいくろんいたじょ":1,"ぬーでぃずむ":1,"ぬるぬるがうごく":1,"ぬすっとじょうご":1,"ぬかづきむし":1,"ぬかごめし":1,"ぬまたまほかる":1,"ぬまづとざんとうかいばす":1,"ぬまびる":1,"ぬきずり":1,"ぬこりん":1,"ぬきあしで":1,"ぬれぞうきん":1,"ぬきがき":1,"ぬおーゔぉとらすぽるとゔぃあっじゃとーり":1,"ぬしこめ":1,"ぬきがた":1,"ぬめぬめ":1,"ぬこすけ":1,"ぬまべ":1,"ぬまくらまなみ":1,"ぬまづこうぎょうこうとうせんもんがっこう":1,"ぬすびとじょうご":1,"ぬかだやえこ":1,"ぬかにくぎ":1,"ぬぐりすんびらんしゅう":1,"ぬけがけ":1,"ぬかだえき":1,"ぬがせし":1,"ぬのきそ":1,"ぬくまる":1,"ぬいしろ":1,"ぬぎすてる":1,"ぬりたかった":1,"ぬけあがる":1,"ぬーどしょー":1,"ぬるぬる":1,"ぬむ":1,"ぬるめる":1,"ぬかたちょう":1,"ぬこびょう":1,"ぬすむ":1,"ぬるぷれい":1,"ぬはさねはかりのなまえでほんとうのなまえは":1,"ぬまたし":1,"ぬがせや":1,"ぬしのけっつはくりけっつ":1,"ぬいかえす":1,"ぬわらえりあ":1,"ぬいなおす":1,"ぬまたゆうすけ":1,"ぬかつきむし":1,"ぬりひろげる":1,"ぬいかた":1,"ぬーさん":1,"ぬめっと":1,"ぬのびきうんどうこうえんりくじょうきょうぎじょう":1,"ぬのせい":1,"ぬれすけ":1,"ぬるめうどん":1,"ぬまべしんいち":1,"ぬめりちょす":1,"ぬまじりおんせん":1,"ぬまざわたかし":1,"ぬかたのおおきみ":1,"ぬーゔぇる":1,"ぬのづつみ":1,"ぬーどさんだる":1,"ぬすびとねこ":1,"ぬこみみだん":1,"ぬるゆ":1,"ぬまくないまこと":1,"ぬこたく":1,"ぬかがふくしろう":1,"ぬれぎぬをきせる":1,"ぬれえん":1,"ぬこぬこだーびー":1,"ぬいはじめ":1,"ぬーどじゅえりー":1,"ぬいいと":1,"ぬのえ":1,"ぬかずきむし":1,"ぬるぽちゃん":1,"ぬーどしゃしん":1,"ぬーす":1,"ぬばたまどり":1,"ぬーどめーかー":1,"ぬしのいけんはすべてきゃっかでいじりたおすほうそう":1,"ぬこみさ":1,"ぬれいろ":1,"ぬりつぶし":1,"ぬれおちば":1,"ぬりてぃむのたみ":1,"ぬっくん":1,"ぬしのあたまはわるい":1,"ぬーぶら":1,"ぬくみずあなる":1,"ぬんとん":1,"ぬじりこくさいくうこう":1,"ぬぼく":1,"ぬのはらえき":1,"ぬりべじんじゃ":1,"ぬいあげる":1,"ぬるしゃちょう":1,"ぬぬぬ":1,"ぬのひきはら":1,"ぬきやまがいせい":1,"ぬかえび":1,"ぬのなぷ":1,"ぬまくまちょう":1,"ぬまわだちょう":1,"ぬかあぶら":1,"ぬえばぐらなだふくおうりょう":1,"ぬのびきとしお":1,"ぬのてーぷ":1,"ぬれる":1,"ぬきあしさしあししのびあし":1,"ぬきうちかいさん":1,"ぬすみよみ":1,"ぬるおた":1,"ぬすまれたよくじょう":1,"ぬう":1,"ぬきて":1,"ぬっちゃ":1,"ぬるいぬるい":1,"ぬーどまうす":1,"ぬれ":1,"ぬぬこ":1,"ぬきしろ":1,"ぬいでいきまいすたー":1,"ぬこしん":1,"ぬかびらおんせん":1,"ぬり":1,"ぬるまゆにつかる":1,"ぬかだひがしごう":1,"ぬいぬい":1,"ぬいぐるめん":1,"ぬーすぱとりおっと":1,"ぬはさね":1,"ぬまとらのお":1,"ぬるまゆしゃんはいきょうだい":1,"ぬーーん":1,"ぬきよみ":1,"ぬいたあとのてぃっしゅかっこはんぶん":1,"ぬきつけ":1,"ぬなみけいおん":1,"ぬるそくほう":1,"ぬましょうぞう":1,"ぬまかげ":1,"ぬか":1,"ぬまづぷろれす":1,"ぬほこ":1,"ぬまくない":1,"ぬこちゅう":1,"ぬらまごごしん":1,"ぬける":1,"ぬーぬーはへんたいしゅくじょしりーず":1,"ぬまべまち":1,"ぬきがたい":1,"ぬしはてんし":1,"ぬまがみつよし":1,"ぬえぽん":1,"ぬまえび":1,"ぬまちのましんおう":1,"ぬかり":1,"ぬぎき":1,"ぬれてであわ":1,"ぬまこ":1,"ぬまづらくーん":1,"ぬらりひょんのまごせんねんまきょう":1,"ぬすと":1,"ぬるねず":1,"ぬるち":1,"ぬりたてる":1,"ぬるーしゅ":1,"ぬれせん":1,"ぬまたよしあき":1,"ぬまじりりゅうすけ":1,"ぬるかわおんせん":1,"ぬこねこあっとしゅゔぁりえ":1,"ぬのはばいっぱい":1,"ぬきあわせる":1,"ぬひかいほう":1,"ぬまづ":1,"ぬかぶくろ":1,"ぬーめん":1,"ぬがなさんぞく":1,"ぬすらせんせん":1,"ぬーんぶらいと":1,"ぬる":1,"ぬくめん":1,"ぬまのはたえき":1,"ぬきげー":1,"ぬつす":1,"ぬしはぁはぁ":1,"ぬまたばく":1,"ぬたくる":1,"ぬんぼ":1,"ぬくみずよういち":1,"ぬしまむら":1,"ぬかみそせんげん":1,"ぬらぬら":1,"ぬのきじのはば":1,"ぬえたんはおれのせんばいとっきょ":1,"ぬきほん":1,"ぬこまっしぐら":1,"ぬぐいとる":1,"ぬこぬこさん":1,"ぬのかわてつろう":1,"ぬなかわひめのみこと":1,"ぬしははげにゃん":1,"ぬすびとをとらえてみればわがこなり":1,"ぬけあな":1,"ぬしはりすなーのいやしだっ":1,"ぬかびら":1,"ぬいもよう":1,"ぬまぶくろんくす":1,"ぬますぎ":1,"ぬるけりゃしばればいいじゃない":1,"ぬめり":1,"ぬすびとたけだけしい":1,"ぬすびとこんじょう":1,"ぬこげいどうがりんく":1,"ぬぅわおれのふらぐっ":1,"ぬっこぬこ":1,"ぬかだみなみごう":1,"ぬのびきちょう":1,"ぬまたすけみつ":1,"ぬきさしならない":1,"ぬれば":1,"ぬくいみなみちょう":1,"ぬけるうらでぃーぶいでぃーたいしょう":1,"ぬくいとくろう":1,"ぬいぐるみさん":1,"ぬかしおる":1,"ぬまくらかわいいよぬーかわいいよぬーまなみ":1,"ぬいとめる":1,"ぬこけーじ":1,"ぬるぬるしてます":1,"ぬきさしならぬ":1,"ぬこと":1,"ぬまおう":1,"ぬいこみ":1,"ぬのびき":1,"ぬめりとり":1,"ぬきあしさしあし":1,"ぬびあいせきぐん":1,"ぬぎょう":1,"ぬのえき":1,"ぬこた":1,"ぬまざわじゃき":1,"ぬーどきゃんぷ":1,"ぬるぽいんたー":1,"ぬいぐるしょう":1,"ぬまべえき":1,"ぬまはぎ":1,"ぬりばん":1,"ぬまくぼ":1,"ぬうっと":1,"ぬすんだばいくではしりだす":1,"ぬまめん":1,"ぬかみそくさい":1,"ぬまぶくろ":1,"ぬぬねねぬぬねの":1,"ぬりたくる":1,"ぬるもじれつ":1,"ぬけにーと":1,"ぬまがえる":1,"ぬのびきちょすいち":1,"ぬかあめ":1,"ぬしはかぎっこ":1,"ぬ":1,"ぬぼりりむげんしょう":1,"ぬぐみん":1,"ぬまゆか":1,"ぬめら":1,"ぬまこや":1,"ぬけがら":1,"ぬれて":1,"ぬかつひ":1,"ぬりこぼし":1,"ぬまづか":1,"ぬっぺっぽう":1,"ぬこまる":1,"ぬっちゃけ":1,"ぬのぎぬ":1,"ぬーべる":1,"ぬのでらあすほ":1,"ぬなみてるえ":1,"ぬえ":1,"ぬりこむ":1,"ぬここ":1,"ぬかぐ":1}