{"わんきるのおに":1,"わふつじてん":1,"わだいさむ":1,"わくせいにびる":1,"わいしーてぃーぴー":1,"わたなべかぞう":1,"わっかないくうこう":1,"わいんれっど":1,"わけがら":1,"わいどろー":1,"わたりこうがいびる":1,"わかむらかいてんずし":1,"わけべ":1,"わかがしら":1,"わんまっち":1,"わしずまーじゃん":1,"わかもりたろう":1,"わたしはぞんびとあるいた":1,"わくせいぜーべす":1,"わんすもあ":1,"わたなべしゅんすけ":1,"わくちんそふと":1,"わたなべみどり":1,"わるふざけしゃしん":1,"わぎり":1,"わかさせいかつ":1,"わたなべなお":1,"わんだーふぁーむ":1,"わらきんおーるすたーず":1,"わんど":1,"わがにほん":1,"わすれるわけないでしょ":1,"わたつみのみこと":1,"わーるどまらそんめじゃーず":1,"わがままきのままあいのじょーく":1,"わんふれーずぶるーす":1,"わびずまい":1,"わかばやしかぶ":1,"わかなどおり":1,"わーるどびじねすさてらいと":1,"わいどばんぐみ":1,"わかばやしじょうあと":1,"わんぱくおうじのおろちたいじ":1,"わーるどほびーふぇすてぃばる":1,"わんだいれくしょん":1,"わいるどかーど":1,"わくわくてかてか":1,"わたな":1,"わたりばし":1,"わかやまけんしらはまちょう":1,"われにかえる":1,"わがこう":1,"わたりしんせいき":1,"わりつけこうぞう":1,"わんるーむじょじし":1,"わかちこ":1,"わらういえもん":1,"わじまん":1,"わりこむ":1,"わめぞ":1,"わんだぴー":1,"わいあれす":1,"わりつけ":1,"われめふんか":1,"わづくえ":1,"わんがんしょ":1,"わんぱくめろ":1,"わたしはえふえふふぉーてぃーんをつづけるよ":1,"わかんやく":1,"わだひろし":1,"わかやまこうえん":1,"わさだにまち":1,"わくわくにちりんらんど":1,"わがみ":1,"わさみそ":1,"わだまあや":1,"わなみともひろ":1,"わいげんご":1,"わかぎしんご":1,"わんせれ":1,"わたなべかずゆき":1,"わんず":1,"わかわかしい":1,"われらわーるど":1,"わたなべりょう":1,"わせだすぽーつ":1,"わたなべみちこ":1,"わいるだー":1,"わだやまちょう":1,"わんぺあ":1,"わがみにたどるひめぎみ":1,"わだづか":1,"わいやぐらす":1,"わんまんしょー":1,"わだそうこう":1,"わらいなく":1,"わしぼん":1,"わかまつじょう":1,"わたゆみ":1,"わかさなめのかみ":1,"わかたけいろかぶ":1,"わーどりーふかぶしきがいしゃ":1,"わいじゅうえむやぎゅうにんぽうちょう":1,"わろりーぬ":1,"わたなべはじめ":1,"わすれお":1,"わごんもーる":1,"わたなべゆい":1,"わけのわからないほも":1,"わかねえ":1,"わにあきら":1,"わーどな":1,"わもんだこ":1,"わかつきとしかず":1,"わずき":1,"わらび":1,"わんげる":1,"わかやまらーめん":1,"わんだーびーとすくらんぶる":1,"わすれじも":1,"わたわたしい":1,"わんわんさんじゅうし":1,"わかばとおり":1,"わざし":1,"わーるどこうげい":1,"わいどびゅー":1,"わらぐつ":1,"わたしはたみーまたあったな":1,"わかおかみ":1,"わーさむはかせ":1,"わきほんじん":1,"わたなべしょうぞう":1,"わかきはいでるべるひ":1,"わかすぎとりこ":1,"わかてしてんのう":1,"わこぴんあいこうかい":1,"わたしというおとひびきそのさきに":1,"わまるけるを":1,"わかもれ":1,"わかりだす":1,"わしづかひろみつ":1,"わいてぃー":1,"わかごう":1,"わぎもこ":1,"わごうりょういち":1,"わかもくん":1,"わりあいに":1,"わよ":1,"わたくしりつ":1,"わかまつたけ":1,"わいぱっくす":1,"わんだーもも":1,"わたしてき":1,"わたながしへん":1,"わかんろうえいしゅう":1,"わきたかず":1,"わーるどたんくみゅーじあむ":1,"わこうしょうじ":1,"わーきんぐかっぷる":1,"わだまさみち":1,"わっかないぶんとんち":1,"わこびあしょうけん":1,"わるいところどり":1,"わづらひのうしのかみ":1,"わかむらめぐみ":1,"わくとりましーん":1,"わしゅきつ":1,"わじまぶんとんきち":1,"わらべ":1,"わなっふううう":1,"わかやまいっく":1,"わこうど":1,"わーるどふっとぼーるにゅーす":1,"わかれみち":1,"わーるどくらしっく":1,"わたなべうらと":1,"わらびーず":1,"わいやーあくしょん":1,"わおけいすう":1,"わっとまんし":1,"わいげん":1,"わだづかえき":1,"わたなべかける":1,"わかやまぎんこう":1,"わだまんきち":1,"わいあーど":1,"わしゅけー":1,"わいえるしゅとらす":1,"わたぱち":1,"わらこら":1,"わかやばし":1,"わーくぷれーす":1,"わかばく":1,"わたらせ":1,"わじんち":1,"わかばやしせりな":1,"わかいずみけい":1,"わずかに":1,"わるざざーと":1,"わんちぇんみん":1,"わーどらっぷ":1,"わすれられる":1,"わいどばっは":1,"わんにゃんのひ":1,"わってみた":1,"わきじとううぇーかた":1,"わいのう":1,"わくわくますこっとむら":1,"わかえだ":1,"わかばちょう":1,"わたなべこういちろう":1,"わいえむおーかけるあいます":1,"わんぱーくこうちあにまるらんど":1,"わるいむすこ":1,"わだこうへい":1,"わくしゅんぞう":1,"わいんらっく":1,"わしのみや":1,"わっほいぼじょう":1,"わたなべけん":1,"わかとば":1,"わきたしろきみ":1,"わーぷろばか":1,"わくいえみ":1,"わるふぁす":1,"わたかの":1,"わしまむら":1,"わーるどいずぼいん":1,"わーすと":1,"わかめざけ":1,"わだあきこさつじんじけん":1,"わたなべきちたろう":1,"わかやまけんりつわかやましょうぎょうこうとうがっこう":1,"わしょくわーるどちゃれんじ":1,"わかむらじお":1,"わるさわだけ":1,"わんこつ":1,"わじま":1,"わはは":1,"わんだうん":1,"わーるどますたーずげーむず":1,"わたべみほ":1,"わーるずえんどあーすほーる":1,"わかまつかわだ":1,"わーげんばす":1,"わんころぐ":1,"わこぷー":1,"わにー":1,"わたりわたる":1,"わらいのつぼ":1,"われんおしょう":1,"わじまとくべつちいききしょうかんそくじょ":1,"わたなべかずあき":1,"わんえいと":1,"わらしせんにん":1,"わじろ":1,"わかとうしょう":1,"わらにんぎょうろんぽう":1,"わかやましわだ":1,"わかせいずみ":1,"わかやましもつこう":1,"わだのりお":1,"わかものめせん":1,"わたなべそうき":1,"わんがんせんし":1,"わかしらが":1,"わんまんしょう":1,"わじお":1,"わだふみお":1,"わいえふじゅうきゅう":1,"わたなべちひろ":1,"わーくすてーしょんびゅーぽーと":1,"わかばやしあき":1,"わんざありあけ":1,"わがはいはてんしである":1,"わんうぇい":1,"わたなべやすこ":1,"わがつま":1,"わたなべかずこ":1,"わわさい":1,"わかやまくい":1,"わいびーあーるひゃくにじゅうご":1,"わきさし":1,"わんにゃんぷー":1,"わいのっと":1,"わだよしあき":1,"わいきょく":1,"わきまさのり":1,"わかすぎなおみ":1,"わかふうふ":1,"わきん":1,"わしんとんしゅう":1,"わかまつぼーとれーすじょう":1,"わらにもすがる":1,"わるいさんにんしゅうら":1,"わいぜっとえふせんあーる":1,"わたなべすみただ":1,"わかいさくんど":1,"わたしがちょうちょうです":1,"わかやまけんだいにく":1,"わたなべかずのり":1,"わせだえき":1,"われやせんにとつにゅうす":1,"わたなべあつむ":1,"わいやーしきでぃすくぶれーき":1,"わかやまでんてつ":1,"わいわいわーるど":1,"わけとん":1,"わりねたい":1,"わすれられるけんり":1,"わあ":1,"われにかえったらまけかなとおもって":1,"わだよりこ":1,"わたしがすぺらんかー":1,"わんがんせん":1,"わげー":1,"わかやまけんさん":1,"わたくり":1,"わたしもり":1,"わるくち":1,"わるいとこどり":1,"わけのひろむし":1,"わな":1,"わりましちんぎん":1,"わしばだけ":1,"わりこみぶんるい":1,"わいるどきゃっつ":1,"わちさんぺい":1,"わたなべつねひこ":1,"わたなべじゅん":1,"わたなべしゅう":1,"わたくしのほうでは":1,"わりおらんどすりーふしぎなおるごーる":1,"わるぐせ":1,"わろす":1,"わがおしえごひとらー":1,"わんでーますたー":1,"わだる":1,"わぶんたいぷらいたー":1,"わらってそとむらさん":1,"わいどう":1,"わたしがすてたおんな":1,"わかやまけいりんじょう":1,"わふう":1,"わたぬきなお":1,"わらしべぷろとこる":1,"わかやまてるひこ":1,"わんどりんくせい":1,"わーるどおおやまからて":1,"わーむうっど":1,"わんたぴー":1,"わかやまけんりつわかやまきたこうとうがっこう":1,"わらし":1,"わたなべあつし":1,"わいひろ":1,"われいしんこう":1,"わしこうさん":1,"わかばえふじゅうきゅう":1,"わこく":1,"わるいたいさ":1,"わけわけ":1,"わしょっき":1,"わんぱくざかり":1,"わふうとう":1,"わーるどえんぶりお":1,"わいけい":1,"わんなうつ":1,"わずかなじかんをみつけてしりーず":1,"わたるんるん":1,"わりだし":1,"わきあずみ":1,"わんことくらそう":1,"わんぴーすすまほ":1,"わさい":1,"わきやく":1,"わんだーぷろだくしょん":1,"わんりゅう":1,"わーくぷれいすらーにんぐ":1,"わんはんどれっどせこんずきっちんばとる":1,"わこんかんさい":1,"わかつきかんな":1,"わきた":1,"わがだけ":1,"わかやません":1,"わんぺだる":1,"わんがんすたじお":1,"わーるどゆーすかっぷ":1,"わへいかいぎ":1,"わすれぐさ":1,"わじゅつけいしゅうかい":1,"わだやまどおり":1,"わせいつ":1,"わかたこういち":1,"わーるどさっかーきんぐ":1,"わたなべあけの":1,"わたなべやよい":1,"わっわぁぅ":1,"わーるどしりーず":1,"わいるどすみす":1,"わんだーふぇすてぃばる":1,"わんたーんきる":1,"わせいほう":1,"わがいえ":1,"わたか":1,"わたなべこうとうがくいん":1,"わたなべひでゆき":1,"わらうかどにはあんこもち":1,"わちゃわちゃ":1,"わたなべきえこ":1,"わらいごえ":1,"わけのわからないことば":1,"わるふざけのよる":1,"わたつき":1,"わいせつ":1,"わだせんかいきょう":1,"わんつーすりーふぉーよろしく":1,"わんくぅ":1,"わさびだいすきごわすまる":1,"わら":1,"わかねちゅり":1,"わかばやしかおる":1,"わだみえ":1,"わんれんぐす":1,"わたがし":1,"わんだーぷろじぇくとじぇい":1,"わかだいしょうしりーず":1,"わりおらんどしぇいく":1,"わくものがたり":1,"わけにはいけない":1,"わかはらまき":1,"わたなべもりつな":1,"わだかまる":1,"わせだだいがくけいぞくわせだじつぎょうがっこうこうとうぶ":1,"わんおくろっく":1,"わーるどおーしゃんふぁーむ":1,"わけがちがう":1,"わたなべつとむ":1,"わたぼー":1,"わりこみほうしき":1,"わははほんぽ":1,"わーるどゆーす":1,"わききゃっちゃーじけん":1,"わーぷ":1,"わんもあたいむ":1,"わるどーかっぷ":1,"わーきんぐうーまん":1,"われわれのぎょうかいではごほうびです":1,"わたなべりな":1,"わげお":1,"わいか":1,"わたぬきだいひょう":1,"わかねんはんざいしゃ":1,"わたなべどおり":1,"わいえっち":1,"わいる":1,"わすれなぐさ":1,"わかばやしえり":1,"わらたば":1,"わたばね":1,"わたしうたいて":1,"わかおうし":1,"わらいのしんぽじうむ":1,"わかのはな":1,"わかばやしかな":1,"わんがんみっどないとのとうじょうじんぶつ":1,"わいるどくりーちゃーず":1,"わいてぃたっち":1,"わたべゆか":1,"わーてるろー":1,"わせだじつ":1,"わたぬきしんとう":1,"わせだこうとうがっこう":1,"わちふぃーるど":1,"わがしゃ":1,"わかはらいちろう":1,"わくいむぎ":1,"わせだいりょうがくえん":1,"わたしじしん":1,"わたなべえんたーていめんと":1,"わるいけどこのどうがさんにんようなんだ":1,"わんじぇさん":1,"わかやまけんけい":1,"わかめおうじ":1,"わこうし":1,"わんちっぷまいくろこんぴゅーたー":1,"わんしゃおろん":1,"わたなべたけさと":1,"わたなべおん":1,"わたなべかよこ":1,"わんだふるわーるど":1,"わりさやじゅり":1,"わいるどあーむずしりーず":1,"わいやらす":1,"わこうじゅんな":1,"わたなべりき":1,"わたしがしょうこ":1,"わたぐも":1,"わいるどたいがー":1,"われいじんじゃ":1,"わかみどり":1,"わからないきじのいちらん":1,"わくわく":1,"わざわざ":1,"わしょくどころ":1,"わださいくる":1,"わりびきじかん":1,"わいつぜっかー":1,"わかむらさき":1,"わたなべあずさ":1,"わびとさび":1,"わきやまえつこ":1,"わりつけはいれつ":1,"わーるどぷれみあむぼくしんぐ":1,"われちゅう":1,"わつきぐみ":1,"わっとちぇっかー":1,"わいてぃ":1,"わかふじちょう":1,"わずらーす":1,"わぶんたい":1,"わかてかがくしゃしょう":1,"わしたにいずみ":1,"わたなべあゆむ":1,"わたしのおきにいり":1,"わふうりょうり":1,"わいやりんぐ":1,"わーるどすまっしゅ":1,"わかつきさら":1,"わすれる":1,"わーきんぐぐるーぷ":1,"わかやまけんりつかいなんこうとうがっこう":1,"わかもとのりお":1,"わだこ":1,"わりつけのながれ":1,"わいぷあうとぱるす":1,"わりかん":1,"わかやまほうそう":1,"われさ":1,"わりざい":1,"わっふーぴー":1,"わきおうかん":1,"わいびーえす":1,"わたりだひとし":1,"わたなべかずみ":1,"わりて":1,"わたしおんなげいにんをめざしてます":1,"わしんとんしきょく":1,"わいるず":1,"わかち":1,"わたげ":1,"わりかた":1,"わたしはおんなになりたい":1,"わりおらんどしりーず":1,"わくも":1,"わらびもちのようせい":1,"わっきち":1,"わろんちいき":1,"わきょう":1,"わんこのおへや":1,"わだい":1,"わいやらっぴんぐ":1,"わたなべしゅん":1,"わしわしさぎ":1,"わきしょうめん":1,"わたなべさちこ":1,"わがやのりょうり":1,"わにばーん":1,"わーるどすきるずいんたーなしょなる":1,"わきむん":1,"わだしゅく":1,"わんだーこーぽれーしょん":1,"わくだまゆこ":1,"わらいだす":1,"わいごゆいしょうこうぐんまっきしょうじょう":1,"わーるうぃんど":1,"わーむかっこゆうぎおう":1,"わたりかずや":1,"わるがきたちがかえってきます":1,"わりこみこんとろーら":1,"わだいのみちしるべ":1,"わくてか":1,"わーぐなー":1,"わくわくすたでぃわーるど":1,"わるいのはあめりか":1,"わちゃごな":1,"わーくそんぐ":1,"わだりょうち":1,"わせだみすてりくらぶ":1,"わかぎみお":1,"わふく":1,"わたくりき":1,"わたししゅやくのあかざあかりです":1,"わたしのねこはおうじさま":1,"わせだびようせんもんがっこう":1,"わんぎり":1,"わぶん":1,"わーるどまっぷ":1,"わかのうら":1,"わりまししょうきゃく":1,"わんてんぽ":1,"わらなわ":1,"わろ":1,"わたなべひでお":1,"わどまち":1,"わんこみ":1,"わたなべまいこ":1,"わたむ":1,"わいあーどのべっく":1,"わるきゅー":1,"わーくあうと":1,"わせいかんご":1,"わかれめ":1,"わがっきばんど":1,"わーどすたー":1,"わんころぴー":1,"わえい":1,"わたなべまとい":1,"わいんていすてぃんぐ":1,"わーるどかっぷじゃーなる":1,"わすれてたことをおもいだした":1,"わいく":1,"わたしちん":1,"わかまつともや":1,"わーくすぺーす":1,"わしつここあ":1,"わみょうしょう":1,"わたなべよしひろ":1,"わたなべたいりく":1,"わーるどにゅーすにちゃん":1,"わかんでゆるす":1,"わっくかぶしきがいしゃ":1,"わさんぼん":1,"わんれん":1,"わっとたいらーのらん":1,"わいやぶらし":1,"わんがんしりーず":1,"わさびーふ":1,"わにとかげぎす":1,"わーきんぐせっと":1,"わけがない":1,"わりびききんゆうさい":1,"わだいせい":1,"わーるどくりーく":1,"わるくちべに":1,"わたくしのばあい":1,"わいるどすぴーどえっくすすりーとうきょうどりふと":1,"わたなべのん":1,"わいごうい":1,"われはなんじ":1,"わたべつばさ":1,"わかものご":1,"わいぜっとえふあーるわん":1,"わどまりちょう":1,"わかまつかわだえき":1,"わいととう":1,"わぶたせんせい":1,"わびいる":1,"わたなべしょうこう":1,"わんぎゃる":1,"わしゅ":1,"われにもあらず":1,"わび":1,"わかめ":1,"わかやまだいがく":1,"わせだだいがくけいぞくわせだじつぎょうがっこう":1,"わたなべよう":1,"わいどすくらんぶる":1,"わいどすくりーん":1,"わんだ":1,"わぎゅうしょうほう":1,"わたなべたもつ":1,"わきさわみき":1,"わせいろなうど":1,"わいやーふぉっくすてりあ":1,"わんだーしてぃ":1,"わかものぶんか":1,"わくわくじゅぎょう":1,"わかいほうのあさみ":1,"わいしーぷろだくしょん":1,"わんこーるそくほう":1,"わへい":1,"わらいじに":1,"わにづかしょり":1,"わかむしゃ":1,"わへいぷろせす":1,"わいもばいる":1,"わーくかんきょう":1,"わいえむおふぃす":1,"わらいのじかん":1,"わーるずえんどだんすほーるぴーぶいりんく":1,"わせいばりおす":1,"わちょ":1,"わじ":1,"わけいせいじゃく":1,"わらういぬ":1,"わご":1,"わかばやしえき":1,"わかやまえき":1,"わーほり":1,"わくわくどうぶつらんど":1,"わこくおう":1,"わだともひろ":1,"わーるどとぴっくさてらいと":1,"わーるどかっぷよせん":1,"わっつぼうどう":1,"わりせんほう":1,"わいぴーえる":1,"わちがいやいとさと":1,"わんだらぴーのちょっとしたおちゃめしりーず":1,"わたしはわたしとたびにでる":1,"わりばせにせんじゅう":1,"わんりゅーみん":1,"わだはやて":1,"わいどがーど":1,"われめちゃん":1,"わにがわ":1,"わたなべこうじ":1,"わたなべねね":1,"わりつけたいしょうたいくらす":1,"わたしはあい":1,"わたわたはるかさん":1,"わらいのきんめだる":1,"わらむら":1,"わかすぎひろし":1,"わたなべおさむ":1,"われい":1,"わかん":1,"わんこーさん":1,"わこん":1,"わいえ":1,"わいりやばい":1,"わたなべかずひさ":1,"わむら":1,"わにもく":1,"わーるどあーむずしんふぉぎあまっど":1,"わるびる":1,"わりだけ":1,"わっはうけいこく":1,"わかばえき":1,"わーぷぎわく":1,"わたなべしゅんめい":1,"わだいこのたつじん":1,"わたくし":1,"わりびきしじょう":1,"わいえすいちいち":1,"わんがんわんだーだーりん":1,"わたびきこう":1,"わけはわかるもの":1,"わーくしょっぷ":1,"わかもとだいかぞく":1,"わこるぷでぃー":1,"わしお":1,"わっはっはー":1,"わろっく":1,"わおんいくと":1,"わかやまけんぎかいぎいん":1,"わたらせけいこくてつどう":1,"わいえむじーおなー":1,"わいしゃつ":1,"わりびきせいど":1,"わきまえる":1,"わかさぬり":1,"わりびきけん":1,"わだちみき":1,"わんばっく":1,"わたしにはゆめがある":1,"わかんひかくぶんがくかい":1,"わふぉがーと":1,"わくしく":1,"わんかっぷおおぜき":1,"わかしゆ":1,"わらいのすみか":1,"わたしょ":1,"わがことなれり":1,"わいるどあーむずあるたーこーどえふ":1,"わたりだいき":1,"わだえりか":1,"わーるどぼうる":1,"わちがいや":1,"わだひろみ":1,"わっしゃ":1,"わたしたちはすごいことをしてしまった":1,"われ":1,"わんわんぐるーぷ":1,"わたなべみか":1,"わんどら":1,"わくがいごーる":1,"わたなべかねんど":1,"わたしのしょうげん":1,"わけのしんのす":1,"わたりだ":1,"わたりどりぴー":1,"わしずあやの":1,"わけあたえる":1,"わいわいどうがりんく":1,"わかもの":1,"わろえない":1,"わんだふるはーつらんど":1,"わたなべことの":1,"わたぬききみひろ":1,"わだまさむね":1,"わびびと":1,"わいるどすぴーど":1,"わたくしする":1,"わたしのじかん":1,"わたりおんせん":1,"わひと":1,"われねぼびこ":1,"わんしんけいそう":1,"わたしのすきなひと":1,"わかす":1,"わすれなぐさしょう":1,"わらうせーるすまん":1,"わかれかい":1,"わにがめ":1,"わさびじょうゆ":1,"わりやすかぶ":1,"わんがた":1,"わたるつー":1,"わたようてるひさ":1,"わたなべてっこう":1,"わるりんご":1,"わたなべあつこ":1,"わんすて":1,"わだまりえ":1,"わにし":1,"わらぞん":1,"わらびこ":1,"わこうがくえん":1,"わくやちょう":1,"わいどばんど":1,"わんわーるど":1,"わらうわらわう":1,"わたりだむかいちょう":1,"わたん":1,"わーなーぶらざーず":1,"わらいふくろう":1,"わるでん":1,"わんちっぷこんぴゅーた":1,"わかさとこうえん":1,"わかさぎあなづり":1,"わしざき":1,"わかむし":1,"わいんくーらー":1,"わんぴーす":1,"わくわくのらん":1,"わぐだぐふゅーちゃりすてぃっくゆにてぃ":1,"わすれっぽい":1,"わいえむにーろくれいはち":1,"わりばしはんたー":1,"わたしにはっぴーばーすでい":1,"わだあきこかっか":1,"わせだよびこう":1,"わかおはるか":1,"わいせつこうい":1,"わかやまかさい":1,"わがとうぞう":1,"わっほいしまんと":1,"わたちゃん":1,"わかものがはなれていったものいちらん":1,"わんわんおーたいさ":1,"わせだじつぎょう":1,"わんびん":1,"わちょーい":1,"われわれのでんどういり":1,"わいやーすぴーど":1,"わたりあほうどり":1,"われはたけだかみである":1,"わいだぶる":1,"わぎゃん":1,"わたなべしょういち":1,"わたなべよしひこ":1,"わんおぺ":1,"わさいきょうしつ":1,"わかつー":1,"わだいふっとう":1,"わりつけるいべつ":1,"わんかがやくきせつへ":1,"わらかす":1,"わりてき":1,"わったん":1,"わーるどかっぷせぶんず":1,"わかれさせや":1,"わーるどざひょうけい":1,"わだはるお":1,"わだたく":1,"わだいてんかんぴー":1,"われものちゅうい":1,"われがね":1,"わとう":1,"わたりもの":1,"わたしおんなやめる":1,"わかいつばめ":1,"わかれわかれ":1,"わんだほー":1,"わつきのぶひろ":1,"わっしょいわじまにあ":1,"わいびー":1,"わんわんものがたり":1,"わん":1,"わたしのやさしくないせんぱい":1,"わくもとみさこ":1,"わが":1,"わかほ":1,"わんちゃん":1,"わかないろ":1,"わたらせえき":1,"わんこしらいぬもみじ":1,"わじまそっこうじょ":1,"わげさ":1,"わかはらえみり":1,"わーくすてーしょんいぞんせぐめんときおくいき":1,"わたりうむびじゅつかん":1,"わまわし":1,"わーるずえんどがーるふれんど":1,"わいるどあっとはーと":1,"わかやぎちょう":1,"わかみや":1,"わらぼうし":1,"わかいやいち":1,"わたなべあきお":1,"わんこーなー":1,"わかやまじょう":1,"わかばやしかんぞう":1,"わかさゆえのあやまち":1,"わたえん":1,"わせださがこうとうがっこう":1,"わださやか":1,"わんすてっぷみゅーじっく":1,"わくわくらいおん":1,"わかさたけだし":1,"わたりどり":1,"わかくさおおはし":1,"わいるどあげいん":1,"わくじんぺい":1,"わあああみゅーじっく":1,"わたりふみあき":1,"わかんむり":1,"わくいこうじ":1,"わだしずか":1,"わたつみじんじゃ":1,"わだあきこものがたり":1,"わいあんどこー":1,"わさびづけ":1,"わたしのかつやはさいこうだぞ":1,"わがいをえる":1,"わかやまあやの":1,"わりめ":1,"わかくして":1,"わしらはあやしいたんけんたい":1,"わとふぉーど":1,"わかむらりえこ":1,"わかみけぬのみこと":1,"わざわいのふ":1,"わたしをすきーにつれてって":1,"わたなべひろのり":1,"わらうぷりごん":1,"わく":1,"わきざかやすはる":1,"わじまおんせん":1,"わたしにもはなさせて":1,"わあああさうんど":1,"わこう":1,"わせだしぶやしんがぽーるこう":1,"わーるどこーりんぐ":1,"わいまっくす":1,"わんことりりー":1,"わかみなと":1,"わたしがこどもだったころ":1,"わるつ":1,"わたなべさとし":1,"わたやりさ":1,"わかしま":1,"わずかなそざいでもできるじゃない":1,"わるいーじ":1,"わしそだ":1,"わたなべともよし":1,"わいつうるふ":1,"わがや":1,"わかれる":1,"わーるどかっぷはんたいでも":1,"わたなべあきよ":1,"わくわくぷよぷよだんじょん":1,"わかめん":1,"わだかんじ":1,"わんがんみっどないとまきしまむちゅーん":1,"わいんせらー":1,"わたなべまあり":1,"わたしたちけっこんしました":1,"わたなべしんいちろう":1,"わいおみんぐじけん":1,"わいちゃんねる":1,"わんめ":1,"わさしま":1,"わたしのわんぴーす":1,"わたべななみ":1,"わちゅうきょうどう":1,"わだつねすけ":1,"わくちん":1,"わたなべゆうすけ":1,"わくせいあとりーむ":1,"われはごっほになる":1,"わきのしたに":1,"わがやのらくえん":1,"わらってゆるして":1,"わるきゅーれろまんつぇ":1,"わかやまこうえんどうぶつえん":1,"わかさのこだいささづけ":1,"わなにかかる":1,"わらびさこ":1,"わらぶきいらか":1,"わかばやしふみえ":1,"わたつきしまいふぁんのせいちりんく":1,"わだまこと":1,"わきぴー":1,"わんが":1,"わゆ":1,"わたくしりつばかれあこうこう":1,"わーどさらだ":1,"わたしってほんとぽんず":1,"わせいご":1,"わたらせじゅん":1,"わふうさらだ":1,"わいんどあっぷぽじしょん":1,"わたりどりにやどりぎを":1,"わんがんたろう":1,"わせだあかでみー":1,"わう":1,"わがこ":1,"わかくさけい":1,"わたなべじょうたろう":1,"わりこみさーびするーちん":1,"わけひさあき":1,"わかい":1,"わーわーきょう":1,"わんうえー":1,"わたなべゆうた":1,"わたなべさくら":1,"わいふぁい":1,"わしくらおんせん":1,"わっくり":1,"わざ":1,"わいるどとらっくす":1,"わことさか":1,"わーくすてーしょんへんかん":1,"わたしにいいかんがえがある":1,"わたなべかおる":1,"わたべまさみ":1,"わつじてつろう":1,"わせだおおさかがくえん":1,"わがいえろしあ":1,"わらしべ":1,"われっこ":1,"わかたかよりひめのみこと":1,"わんわんする":1,"わーくすてーしょんしゅべつ":1,"わるだっしゃ":1,"わだかまり":1,"わかなひめ":1,"わっきー":1,"わたなべあきのり":1,"わりこみれじすた":1,"わけわかめ":1,"わかいんきょ":1,"わかこざけ":1,"わいえーおーあい":1,"わたなべきはちろう":1,"わぶるべーす":1,"わくせん":1,"わかいずみせいぞう":1,"わーるどですとろいやー":1,"わかやまけんわかやましあきづき":1,"わたりまさひと":1,"わんうぇー":1,"わーわーさっかー":1,"わくらん":1,"わたりがわ":1,"われをわすれる":1,"わたなべともえ":1,"わるすてるだむ":1,"わりかんじゃぱん":1,"わさびえんそうしゃ":1,"わかへびあんさー":1,"わたなべみちお":1,"わがうるわしのばれんしあ":1,"わいえむしょうけん":1,"わきたやすひと":1,"わたなべみゆき":1,"わーぷろせんようき":1,"わふー":1,"わんだーぱーらー":1,"わんつーちー":1,"わこうしゅっぱん":1,"わたしのりれきしょ":1,"わるきゅーれえいが":1,"わかなはなび":1,"わらこ":1,"わだみさきせん":1,"わたなべのりこ":1,"わたなべこうだい":1,"わたしこみ":1,"わかつきちはる":1,"わすれんぼう":1,"わなわな":1,"わにをしている":1,"わいやれすまいくろほん":1,"わたなべみのる":1,"わいぴんぐ":1,"わこうただお":1,"わかあゆ":1,"わんだーらんどえきで":1,"わたなべまさる":1,"わずらいつく":1,"わんりきー":1,"わしざきたけしのあにめろしんじんおーでぃしょん":1,"わくとれん":1,"わだとしひろ":1,"わらっていいともこーなーすずきふくたんとう":1,"わかばだいみなみ":1,"わりとー":1,"わごころとんかつあんず":1,"わりこみべくた":1,"わどうかいほう":1,"わーすぶれいど":1,"わこまりあ":1,"わっしょ":1,"わっくはるがっしゅくにせんじゅう":1,"わこうどうきょうだん":1,"わたぬき":1,"わただ":1,"わらうさんにんしまい":1,"わことおんせん":1,"わたしにかてるかな":1,"わたなべくにと":1,"わくむすびのみこと":1,"わたなべちほ":1,"わがこころ":1,"わたしがいうまえにだきしめなきゃね":1,"わだいなう":1,"わだせんしゃ":1,"わたつみのかみ":1,"わんもあちゃったー":1,"わたしがかれをころした":1,"わりびきはっこう":1,"わたしはみーむ":1,"わどうかいちん":1,"わせだじつぎょうがっこう":1,"わじろひがた":1,"わたしきになります":1,"わたなべひろみち":1,"わーうーぱーるーぱー":1,"わたなべぼくしんぐじむ":1,"わかまつみゆき":1,"わいんいろ":1,"わかのなみ":1,"わーくねっと":1,"わたなべまつお":1,"わかやまとういん":1,"わかやまけんどうひゃくななじゅうななごうせん":1,"わかやまちさい":1,"わたなべよしみ":1,"わっさー":1,"われわれのすぱろぼ":1,"わっぷ":1,"わーるずえんどたんすほーる":1,"わんだふるらいふ":1,"わたりてつやたんじょうさい":1,"わたらいふ":1,"わそうこもの":1,"わたなべあゆみ":1,"わたなべわたる":1,"わなび":1,"わりかのこ":1,"わたしはてんねんじゃないでござるよ":1,"わかれをつげる":1,"わにばなな":1,"わらけずり":1,"わたぼうし":1,"わりんご":1,"わかやまかいじょうほあんぶ":1,"わいゔぁーん":1,"わせだだいがくゆうべんかい":1,"わんとう":1,"わんだーらんどおんらいん":1,"わいるどすとーむ":1,"わだだいがく":1,"わたらいひろぶみ":1,"わたなべひさよし":1,"わかめぱっつん":1,"わいせつぶつ":1,"わーくるーるけんてい":1,"わたなべひさえ":1,"わかみたまのかみ":1,"わだがはら":1,"わかばやしひろゆき":1,"わくわくぴー":1,"わたんじ":1,"わたなべひなこ":1,"わいんからー":1,"わかせがわ":1,"わかぞのしょうがっこう":1,"わぁいうすしおあかりうすしおだいすき":1,"わんぺな":1,"わかいはんじ":1,"わるいね":1,"わいわい":1,"わかったつもりいじんでん":1,"わおきつねざるぞく":1,"わかやましちょう":1,"わーるどざひょう":1,"わだけいこ":1,"わーるどぐらんぷりしりーず":1,"わかのやま":1,"わたなべみちたろう":1,"わけあう":1,"わんじんれい":1,"わりびききっぷ":1,"わいどにゅーす":1,"わだとうげ":1,"わるつのなぽれおん":1,"わごん":1,"わらってはいけないしりーず":1,"わかまつしゅんた":1,"わこうともお":1,"わっとー":1,"わしおさぶろう":1,"わたしのみらいのおむこさま":1,"わる":1,"わたなべけいこ":1,"わんぱくぼうず":1,"わさびおん":1,"わかきゔぇるてるのなやみ":1,"わーなーぶらざーす":1,"わたしたちのさいりょう":1,"われわれのかきゅうようかい":1,"わりこみべくとる":1,"わおう":1,"わかまつかいじょうほあんぶ":1,"われわれのしゅうはではじんとくです":1,"わんくっしょん":1,"わりばしでふるすいんぐ":1,"わるたー":1,"わかたけたくま":1,"わんぱくよこづな":1,"わたぽん":1,"わかしゃも":1,"わーくすあぷりけーしょんず":1,"わたぼう":1,"わんおふ":1,"わかやままなみ":1,"わーるどびくとりーろーど":1,"わおんしば":1,"わかしゅかぶき":1,"わんおぺれーしょん":1,"わらえるわらめ":1,"わーるどさいばーげーむず":1,"わいまーるきょうわこく":1,"わたなべちか":1,"わかさぎひめ":1,"わんもあらぶうえい":1,"わかいちから":1,"わどれ":1,"わなぱーてぃ":1,"わかくほん":1,"わかぐ":1,"わんはんどつりーまん":1,"わいるどぴっち":1,"わたなべしゅうぞう":1,"わいぴーえー":1,"わせりん":1,"わたんかづなり":1,"わりたがね":1,"わんくりっくけいやく":1,"わだいのしんそう":1,"わさゆきこ":1,"わかさわんこくていこうえん":1,"わこうどうじん":1,"わたり":1,"わんるーむあぱーと":1,"わざとですよわざとわざと":1,"わしたしょっぷ":1,"わーなーぱいおにあ":1,"わんだーぼいす":1,"わーくすてーしょんうぃんどう":1,"わんわんぽりす":1,"わかいけいやく":1,"わかやなぎ":1,"わせみす":1,"わらえる":1,"わーかーぷろせす":1,"わせいちゃっぷりん":1,"わすればなのしょう":1,"わだうらえき":1,"われわれはばいどちきゅうにうまれちきゅうにおわれたもの":1,"わさどら":1,"わーくべんち":1,"わかたか":1,"わたなべなおと":1,"わんずふぁくとりー":1,"わたけん":1,"わたしじんるいはすいたいしました":1,"わしずさまふぁんくらぶせんようまっど":1,"わたなべまみ":1,"わきわきかーにばる":1,"わっかないおんせん":1,"わーくぐるーぷねっとわーく":1,"わたら":1,"わいこくこく":1,"わたなべとおる":1,"わくせいめておす":1,"わたなべようじ":1,"わんしーんわんかっと":1,"わかむらぼ":1,"わくいだいすけ":1,"わにゅうどう":1,"わかてるあっとひんけつしょうじょぴー":1,"わかたけななみ":1,"わりおころしあむ":1,"わぐら":1,"わだきょうへい":1,"わたあめじゅうえんらしい":1,"わしゅうじょーじ":1,"わっはー":1,"わらこんしき":1,"わらいぶくろ":1,"わらわれるかんこく":1,"わらびーすくーる":1,"わいすく":1,"わらわ":1,"わがうたぶぎうぎ":1,"わわ":1,"わっふるすらぶ":1,"わかいはやと":1,"わつじてつろうしょう":1,"わかもと":1,"わたのみ":1,"わとるばーど":1,"われちゅうぴい":1,"わーくるーる":1,"わすからんこくりつこうえん":1,"わかびしちょう":1,"わきやりょうた":1,"わーどろーぶ":1,"わがいえいすらえる":1,"わたいれ":1,"わかみやけんじ":1,"わたらー":1,"わせだせつりょう":1,"わかやままち":1,"わたなべつねお":1,"わーどぱっど":1,"わきやゆうじ":1,"わらさ":1,"わろんちほう":1,"わんだーどりーまーほしりっきー":1,"わしにもおぼえがある":1,"わたなべじゅんいち":1,"わたりかに":1,"わかみやどおり":1,"わらいばなし":1,"わがつ":1,"わしんとんほてるぷらざちぇーん":1,"わがまちぎにあ":1,"わたなべかずひろ":1,"わせいことりさばすさまわぁい":1,"わかむらぱう":1,"わだつよし":1,"わしゃ":1,"わけしり":1,"わんこいんふぃっとねす":1,"わでぃだうか":1,"わしぽん":1,"わかきゆうしゃたち":1,"わんだらーずふろむいーす":1,"わだのりこ":1,"わくにはまった":1,"わふうであるひつようせい":1,"わたなべなつな":1,"わーるどすたじあむ":1,"わんだときょぞう":1,"わいしんせい":1,"わびいし":1,"わやまおんせん":1,"わかもとせいやく":1,"わかばりな":1,"わさびのき":1,"わかめすーぷ":1,"わかめぴー":1,"わーるどかっぷばれー":1,"わたなべやすひさ":1,"わたなべなおこ":1,"わだまねーじゃー":1,"わかばやしまさとし":1,"わんわんわんなんだーわん":1,"わるくなる":1,"わたみふーどさーびす":1,"わろしっ":1,"わただまさる":1,"わたしちゃん":1,"わたなべかざん":1,"わたなべえり":1,"わけめん":1,"わたなべまこと":1,"わりぶしん":1,"わんはんどれっとえいとどらごん":1,"わしおみき":1,"わたしばし":1,"わかもとのりあき":1,"わりはん":1,"わちき":1,"わたなべしんいち":1,"わだえみ":1,"わらしごと":1,"わいりょく":1,"わかきりんしんいち":1,"わきまち":1,"わやく":1,"わかみやさだつぐ":1,"わーずわーすのぼうけん":1,"わいおみんぐしゅう":1,"わきえき":1,"わどうりゅう":1,"わせだだいがくけいぞくわせだじつぎょうがこうちゅうとうぶ":1,"わんつーふぃにっしゅ":1,"わりこー":1,"わしおけいじ":1,"わすれえぬきみへ":1,"わんびあえすいちさん":1,"わりびきせいさく":1,"わけとる":1,"わーるどじょしぷろれすでぃあな":1,"わしょくじょう":1,"わらえるこいはしたくない":1,"わるつおう":1,"わかわか":1,"わけにはいきません":1,"わがさいゆうき":1,"わしみやまち":1,"わたしのかれはせんごくぶしょう":1,"わたなべひでのり":1,"わげい":1,"わぐなす":1,"わかきちょうみなみ":1,"わせださい":1,"わんぴーすふぃるむすとろんぐわーるど":1,"わーるどふぁいてぃんぐぶる":1,"わたなべひろこ":1,"わんさくん":1,"わかくさものがたり":1,"わいるどぶらすたー":1,"わいおう":1,"われめたい":1,"わんじひょん":1,"わたぬきろん":1,"わしんとんかいぐんぐんしゅくじょうやく":1,"わっかないしんようきんこ":1,"わかりよい":1,"わかいしゃかい":1,"われわれ":1,"わたしのしごとかん":1,"わずらう":1,"わかたけまち":1,"わくばんれんしょう":1,"わんぷらいすしょっぷ":1,"わしまいやー":1,"わけありべやのつづき":1,"わかいはんじけんじ":1,"わどうおんせん":1,"わおーんぴー":1,"わーるどりーぐ":1,"わんだーももーい":1,"わーくぱーみっと":1,"わかなべりょうた":1,"わんぽいんと":1,"わた":1,"わだかまりなく":1,"わたつきのよりひめ":1,"わんだーぶりっじ":1,"わいびーわん":1,"わいえすえす":1,"わださくらこ":1,"わさびぴー":1,"わーぷすてーしょんえど":1,"わーきんぐまざー":1,"わたなべごうはち":1,"わいどぅーゆーすてっぷ":1,"わにぶちはるこ":1,"わきざ":1,"わきづくえ":1,"わりこみ":1,"わんたいむぱすわーど":1,"わりおらんど":1,"わきょうかい":1,"わー":1,"わかりかねる":1,"わたりひろし":1,"わるぷるぎすのてーま":1,"わふうそうほんけ":1,"わいす":1,"わにがわきくお":1,"わだみさとみ":1,"わいえぬけーじゃぱん":1,"わしりゅう":1,"わかたけてい":1,"わせだちゅうがっこう":1,"わんきょくぶ":1,"わかぞう":1,"わがどぅぐー":1,"わかやまこうえき":1,"われちゅうがげんそういり":1,"わしおいさこ":1,"わけわかりましぇーんかっこくしょう":1,"わでぃ":1,"わまきこうすけ":1,"わいどらんさーびす":1,"わこびたーる":1,"わくわくふじいらんど":1,"わんこいんたくしー":1,"わかこ":1,"わがとう":1,"わいすだん":1,"わーずわーす":1,"わいえむしーえー":1,"わたなべかつみ":1,"わとすん":1,"わざもの":1,"わらしべちょうじゃ":1,"わかみやはちまんしゃ":1,"わたりろうかはしりたい":1,"わんでれ":1,"わかがえり":1,"わかばやしあつし":1,"わるしゃわろうどうか":1,"わくしにあういるす":1,"わたしはぴあの":1,"わんたっちかれー":1,"わたなべぜんたろう":1,"わこうどう":1,"わびじょう":1,"われらのかみ":1,"わかさほんごう":1,"わよう":1,"わかひこのかみ":1,"わたしをやきゅうにつれてって":1,"わだち":1,"わこでふぁいでふぉん":1,"わどるでぃ":1,"わかこひめもえ":1,"わーぷすぺーす":1,"わいるどはーふ":1,"わかちとる":1,"わしんとんぽすと":1,"わせだまち":1,"わーるどぷっちげーむ":1,"わりゃーぐ":1,"わいどぼでぃき":1,"わだりゅう":1,"わじん":1,"わがはんせい":1,"わたべゆみ":1,"わーにんぐなしに":1,"わこ":1,"わがしゅうのと":1,"わたりろうかはしりたいせぶん":1,"わどるのすけ":1,"わらいごと":1,"わーかーずこれくてぃぶ":1,"わりおらんどつーぬすまれたざいほう":1,"わんだこん":1,"わづま":1,"わがぐん":1,"わたいたけはる":1,"わたしのめしあさま":1,"わになしぞく":1,"わるぶる":1,"わるらす":1,"わりばん":1,"わかつきし":1,"わんうぇいびん":1,"わたべだいすけ":1,"わかれごう":1,"わたくしごと":1,"わくい":1,"わたしのどれいになりなさい":1,"わんがんせんそう":1,"わらげ":1,"わだがきけんぞう":1,"わたる":1,"わくあんていちょうせいいんかい":1,"わんすとっぷさーびす":1,"わかまつえいすけ":1,"わしおえいいちろう":1,"わしょくぜん":1,"わかがえる":1,"わいんに":1,"わるふぁりん":1,"わたしのこえがきこえますか":1,"わかさけ":1,"わけのわかったひと":1,"わかったさん":1,"わんだーそん":1,"わきあいあい":1,"わだすみお":1,"わけどり":1,"わらのたて":1,"わいあ":1,"わかやま":1,"わたなべとものり":1,"わきおり":1,"わいどしょー":1,"わかし":1,"わんだふるぱわふるみゅーじっく":1,"わつじしょう":1,"わきのさわ":1,"わんだーぷろじぇくとじぇいつーこるろのもりのじょぜっと":1,"わたせそういちろう":1,"わけいい":1,"わごんさーびす":1,"わけぐん":1,"わーちゃい":1,"わぴー":1,"わりちゅう":1,"わんないとじごろ":1,"わこにゃん":1,"わたなべみよこ":1,"わきあせ":1,"わっかないかいじょうほあんぶ":1,"わーどぷろせっさ":1,"わたのくにほし":1,"わかてあにめーたーいくせいぷろじぇくと":1,"わいずまん":1,"わいのこどうぴー":1,"わいと":1,"わさぶ":1,"わるくちをいう":1,"わるべ":1,"わるぷるぎすのよる":1,"わるば":1,"われらたつきふぁみりー":1,"わるきゅりえ":1,"わけいっさく":1,"わんだん":1,"わぁい":1,"わかつきあやこ":1,"わいんばーぐ":1,"わんぱんまん":1,"わっきんぐ":1,"わりくさび":1,"わたなべえりこ":1,"わーるどおぶふぁいなるふぁんたじー":1,"わたなべいびー":1,"わーすとあにめすれ":1,"わいけーえむえす":1,"わんしーん":1,"わきがきん":1,"わるいことしたさかー":1,"わせだだいがくけいぞくわせだじつぎょうがっこうしょとうぶ":1,"わすれられたつばさ":1,"わいとう":1,"わくせいめふぃうす":1,"わるかわ":1,"わーるどすたんだーど":1,"わたぐものおなか":1,"わさお":1,"わたなべふみき":1,"わりあて":1,"わりおわーるど":1,"わたなべきゅう":1,"わだけんいち":1,"わっこのきんめだる":1,"わかばかつみ":1,"わいせんしょくたい":1,"わだがはらえき":1,"わんらおじー":1,"わたなべあさみ":1,"わんもあきす":1,"わかしろうね":1,"わたしのからだはあたまがいい":1,"わいやれすあだぷた":1,"わしがそだてた":1,"わいりーこよーて":1,"わたりてつや":1,"わだかるしうむせいやく":1,"わかて":1,"わいるどらっしゅ":1,"わふっなごみひこう":1,"わかばだい":1,"わらこういち":1,"わんわんおにちゃんねるまとめ":1,"わりびきてがた":1,"わいるどあーむずざふぃふすゔぁんがーど":1,"わらいおとこくろ":1,"わしん":1,"わらってみた":1,"わたおに":1,"わいあーるせいじん":1,"わっでんかい":1,"わんだーらいふ":1,"わかいけんじ":1,"わこうけんしゃく":1,"わかまつちょうひがし":1,"わせ":1,"わかみやじま":1,"わだりゅうじ":1,"わびすけ":1,"わきおにぎり":1,"わたしはわたしのみちをいく":1,"わきみこほいほい":1,"わらいのちょうしんせん":1,"わけ":1,"わるぷるぎすのよるのいんむ":1,"わせだだいがくけいぞくわせだしぶやしんがぽーるこう":1,"わかんぽう":1,"わんいんち":1,"わたなべぷろだくしょん":1,"わんだとだいやとさやしいやつら":1,"わたべ":1,"わたなべゆういち":1,"わかまつごう":1,"わかばやしもりあき":1,"わーずぎあ":1,"わむし":1,"わかくさかをる":1,"わっしゅわにわに":1,"わたぬきまきこ":1,"わいやーどろじっく":1,"わかきりん":1,"わかばやしかぶにせい":1,"わーるどめいと":1,"わぽる":1,"わいどすくりーんばろっく":1,"わんはんどれっど":1,"わりちゃ":1,"わけはなす":1,"わごと":1,"わかおうじ":1,"わいしょういんけい":1,"わたなべみな":1,"わるわるだんいちりぷじっこういいんかい":1,"わいしー":1,"わっきーぷりんせす":1,"わんまんばす":1,"わろうそく":1,"わきがわ":1,"わーるどすーぱーじょっきーずしりーず":1,"わいないな":1,"わんこーる":1,"わせだしょうちく":1,"わたしがかんがえるまるまる":1,"わがやのおいなりさま":1,"わかおうじいちご":1,"わかば":1,"わふうべんとう":1,"わさびでん":1,"わかまつや":1,"わらうみかえる":1,"わらいぼん":1,"わっとめーたー":1,"わどうりゅうからてどうれんめい":1,"わたなべちぇる":1,"わらびなわ":1,"わっとびょう":1,"わきざし":1,"わざわいをてんじてふくとなす":1,"わきあけ":1,"わたらいけいじ":1,"わりびきさい":1,"わいわいほーむぺーじ":1,"わきのだえき":1,"わるなすび":1,"わすれじのおもかげ":1,"わーるどうごめもぎゃらりー":1,"わかむらぴー":1,"わんわんぱらだいす":1,"わきはまのりこ":1,"わだちょう":1,"わかぎちょう":1,"わたなべしんや":1,"わせだだいがくまにふぇすとけんきゅうしょ":1,"わたなべりかこ":1,"わがしや":1,"わたなべやすよし":1,"わんちっぷまいくろこんぴゅーた":1,"わかやか":1,"わんつーぱんち":1,"わかやまこうぎょうこうとうせんもんがっこう":1,"わだむら":1,"わんがんふー":1,"わだらぢを":1,"わだぼりこうえん":1,"わーわー":1,"わいじん":1,"わくん":1,"わーるどぐらんぷり":1,"わいぴー":1,"わるふざけをする":1,"わりではらう":1,"わたりぐん":1,"わくわくわくせいぷりんせす":1,"われる":1,"わんだーあげいん":1,"わくわくたからじま":1,"わたつみゆうり":1,"わかればなし":1,"わかうかのめのかみ":1,"わこもの":1,"わたよしせいか":1,"わいまーる":1,"わいぷろじぇくと":1,"わかおあやこ":1,"わごんず":1,"わたしがもてないのはどうかんがえてもおまえらがわるい":1,"わかてぎいんのかい":1,"わがよのあきがきた":1,"わんげつじょう":1,"わらいのうず":1,"わたなべのぼる":1,"わたなべえいいちろう":1,"わかくさのしゃるろっと":1,"わたなべよしこ":1,"わぎりのそるべ":1,"わいどびゅーとうかい":1,"わんふぇい":1,"わこうじ":1,"わらったくま":1,"わらういぬのじょうねつ":1,"わかちゃん":1,"わんわんじゃぱん":1,"わんわんどうが":1,"わかもーれ":1,"わいおー":1,"わめきたてる":1,"わくれん":1,"わーどぷろせっさー":1,"わでぃらむ":1,"わんちゃお":1,"わんだー":1,"わふつ":1,"わるしゃわじょうやくきこう":1,"わしはまいおりた":1,"わたなべしずむ":1,"わんらいなー":1,"わかさりな":1,"わたみ":1,"わなびにゅーす":1,"わたぬきのついたち":1,"わしつ":1,"わいよりか":1,"わーるういんど":1,"わかもとちるの":1,"わたりぶね":1,"わいるどしんぐす":1,"わだけい":1,"わかはげ":1,"わいふゆうすけ":1,"わかばやしみつる":1,"わんせぐ":1,"わかばやししほ":1,"わがしじょうのあい":1,"わかづくりうつ":1,"われもの":1,"わんもあらぶりー":1,"わらいおとこ":1,"わみょう":1,"わだしずお":1,"わるひほっふぁー":1,"わしんとんしゅうりつだいがく":1,"わんだーふーる":1,"わいせんしょくたいはぷろぐるーぷ":1,"わくぐみ":1,"わんしんりん":1,"わるびれる":1,"わがえいこう":1,"わびごと":1,"わんふぁいんでい":1,"わかばやし":1,"わかさん":1,"わいてぃーでぃー":1,"わっしょいたけだ":1,"わいんばーぐさらむりろん":1,"わかやまけんりつとういんちゅうがっこうこうとうがっこう":1,"わらびもち":1,"わかつきひかる":1,"われてきあいこうせいんとせいや":1,"わーるどらんきんぐ":1,"わしづか":1,"わじろひがし":1,"わらいぐさ":1,"わんくーるのれぎゅらーよりいっかいのでんせつ":1,"わいぷ":1,"わかやまだいがくまえ":1,"わーねば":1,"わどくじてん":1,"わかめいろ":1,"わんつ":1,"わだたくみ":1,"わらびのまつり":1,"わこうまさひろ":1,"わたはるかさんさぎ":1,"わけじょう":1,"わしんとんかいぎ":1,"わたりださんのうちょう":1,"わがはいはねこである":1,"わーずかなそざいをみつけてしりーず":1,"わかいやすひこ":1,"わかやまちけん":1,"わすいーつ":1,"わざましん":1,"わらびたい":1,"わがままなかたおもい":1,"わたなべしんしょう":1,"わらばんし":1,"わたなべつなや":1,"わろすわろす":1,"わんだーどろっぷ":1,"わたはるか":1,"わっか":1,"わかもときょんとき":1,"わんおう":1,"わたなべまきこ":1,"わくせいそらりす":1,"わーるどすけーる":1,"わきえ":1,"わらわらけい":1,"わたしはげーむをつづけるよ":1,"わけじんじゃ":1,"わかれのうた":1,"わたべたかし":1,"わたなべしげき":1,"わけじゃない":1,"わかなかおり":1,"わるきー":1,"わかやまけん":1,"わかわかしさ":1,"われたたまご":1,"わかつきめぐみ":1,"わかばのころ":1,"わくてかぴー":1,"わんくーる":1,"わたなべりゅううさく":1,"わんつーさんしー":1,"わたなべまり":1,"わやんくり":1,"わんかるび":1,"わるさん":1,"わすれなぐさいろ":1,"わかみやおおどおり":1,"わーくふぉーす":1,"わっきーず":1,"わたべえみ":1,"わかにゃん":1,"わるいおとこ":1,"わさま":1,"わたらせゆうすいち":1,"わけしまかのん":1,"わいやーふれーむもでる":1,"わかまつひろき":1,"わこわっこ":1,"わがく":1,"わたなべまさんど":1,"わっはまん":1,"わしゃにんしき":1,"わにのほん":1,"わかもとる":1,"わたうち":1,"わりこみはんどら":1,"わかいりきゆうき":1,"わの":1,"わけではない":1,"わりにあう":1,"わらぅせぇるすまん":1,"わたなべけいいち":1,"わりこみしんごう":1,"わじへみすふぃあ":1,"わらにんぎょう":1,"わんずれんたかー":1,"わきたやすひろ":1,"わいだ":1,"わかこまぷろ":1,"わたしです":1,"わらんべ":1,"わーるどだがしくらしっく":1,"わーくすてーしょん":1,"わがぜんれいのほくとざんかいけん":1,"わらびのともや":1,"わかやまとみさぶろう":1,"わいぴーいーおー":1,"わんもあせっ":1,"わこんようさい":1,"わるしやわ":1,"わんぱくぱらだいす":1,"わっしょいはうす":1,"わんないとがーる":1,"わんえいとせぶん":1,"わたなべまよ":1,"わんりょく":1,"わんぱたん":1,"わたなべひでたけ":1,"わだあやか":1,"わかとのばら":1,"わらわずぎらいおうけっていせん":1,"わいるどわんず":1,"わすぷ":1,"わかしお":1,"わんぴーすふぃるむぜっと":1,"わたなべまさひろ":1,"わたりえき":1,"わさびな":1,"わりだしえき":1,"わたしのちいさなぴあにすと":1,"わらがいこういち":1,"わきともひろ":1,"わだかつ":1,"わかちがたい":1,"わかこうしょう":1,"わりびく":1,"わりと":1,"わーくあらうんど":1,"わどけい":1,"わけのわからない":1,"わきめもふらずに":1,"わんうぇいこんとろーる":1,"わろう":1,"わこうようちえん":1,"わいどぼーる":1,"わびごえ":1,"わたしをでーとにつれてって":1,"わどめ":1,"わらびしゅく":1,"わたあめぴー":1,"わらいりょうほうし":1,"わさびーむ":1,"わーくぶっく":1,"わさびたいし":1,"わかいがわ":1,"わいしょうふきそくぎんが":1,"わすれがたい":1,"わたのしげる":1,"わただみつとし":1,"わしゅうごう":1,"わーどぷろせっしんぐ":1,"わりおさん":1,"わかなみさと":1,"わがつまよしこ":1,"わかみずやえこ":1,"わなびー":1,"わかなつ":1,"わいけーけー":1,"わいまる":1,"わーるどですとらくしょん":1,"わんすとっぷ":1,"わんこそばまんじゅう":1,"わんだーぼーい":1,"わきがはやい":1,"わーてるろーのたたかい":1,"わいどえきしょう":1,"わきあがる":1,"わかいかずち":1,"わんこるしるふる":1,"わりとどうでもよい":1,"わだべん":1,"わたなべいっぷ":1,"わきさかゆりか":1,"わしゅうざん":1,"わらういぬのはっけん":1,"わーどぱーふぇくと":1,"わらるー":1,"わしづかみ":1,"わかれをおしむ":1,"わっくすだつもう":1,"わいれあしゅっぱん":1,"わくもく":1,"わるいかぜ":1,"わとそんゆっくりじっきょうぷれいやー":1,"わかてんろう":1,"わーるどさっかーまがじん":1,"わんだーしあとる":1,"わくない":1,"わっ":1,"わどうくろやえき":1,"わたらいかずみ":1,"わかくさのころ":1,"わこうほんてん":1,"わんがんくるってぃーんちのあかつき":1,"わかやまけんきょいくいいんかい":1,"わりましきん":1,"わいえいちしーもち":1,"わだいびず":1,"わーるどがん":1,"わたしたちはぜったいにぜったいによりをもどしたりしない":1,"わいるどはーつ":1,"わだまちえき":1,"わたなべひろゆき":1,"わかまおう":1,"わいわくせい":1,"わかみやど":1,"わらく":1,"わかいすう":1,"わかめりんく":1,"わかづるちょう":1,"わんだば":1,"わぐねりあん":1,"わたなべかずまさ":1,"わかきちょうひがし":1,"わいてぃーけー":1,"わかきししたち":1,"わるふぁりんざい":1,"わろすきょくせん":1,"わだがわ":1,"われず":1,"わきみち":1,"わんるーむきっちん":1,"わしざ":1,"わかなえていしょく":1,"わんだりんぐりぺあ":1,"わたるぴー":1,"わーるどぶりっつおやま":1,"わいふぁいはいしんちゅう":1,"わたい":1,"わかる":1,"わたなべちるのかっこきゅうかっことじ":1,"わんちゅくけ":1,"わなごな":1,"わんだーらんど":1,"われめ":1,"わんだーけい":1,"わーるどねばーらんど":1,"わとうし":1,"わたなべちえ":1,"わかるわ":1,"わんぽいんとれっすん":1,"わたなべひさし":1,"わないぴー":1,"わらしなまま":1,"わたしのてんき":1,"わさびだいこん":1,"わいえす":1,"わがこと":1,"わかしゅう":1,"わじまぬり":1,"わりとときめくくとぅるふしんわとーくろーるぷれいんぐげーむ":1,"わたなべよういち":1,"わりした":1,"わいせつのれんますたー":1,"わたなべりゅういち":1,"わたしのおとこ":1,"わがやのゆうしょく":1,"わいわいよんこまげきじょう":1,"わたりうむ":1,"わだたかあき":1,"わがものがお":1,"わたなべりお":1,"わじろまち":1,"わたなべぢゅんいち":1,"わたりべよしのり":1,"わーるずえんどだんすほーる":1,"わいるどふらわーず":1,"わるいことはできぬもの":1,"わかやままりーなしてぃ":1,"わきせいざぶろう":1,"わいえふにじゅういち":1,"わっつ":1,"わいえふにじゅうきゅう":1,"わいらい":1,"わいひー":1,"わけがわからないえすでぃーがんだむまどかまぎか":1,"わしじぬし":1,"わんがりまーたい":1,"わかさひとりじめ":1,"わらたす":1,"わだどん":1,"わかばやしひとし":1,"われさきに":1,"わたなべもとのり":1,"わたるせけん":1,"わんてんかめら":1,"わいんおーぷなー":1,"わおようか":1,"わたなべゆうきち":1,"わかくさどおりしょうてんがい":1,"わかじ":1,"わたなべまさこ":1,"われき":1,"わびちゃ":1,"わげ":1,"わがりゅうをみよ":1,"わたなべいっけい":1,"わるっぽい":1,"わたなべかずま":1,"わくせいじょうせいうん":1,"わたしのこじんしゅぎ":1,"わたりがわのたたかい":1,"わいせつぶつちんれつざい":1,"わしりーわしーりえゔぃちれおんちぇふ":1,"わくいるみ":1,"わさだいすけ":1,"わるいことしましょ":1,"わりす":1,"わかたかぶーむ":1,"わたみぐるーぷ":1,"わんだーらんでぃか":1,"わかさわん":1,"わたなべけい":1,"わがくにのそんりつ":1,"わいるどあーむず":1,"わぎゃんらんど":1,"わんからっと":1,"わたなべだいごう":1,"わりいし":1,"われはろぼっと":1,"わさみん":1,"わーるどぷろれすりんぐ":1,"わかさてつどう":1,"わんいーうぇいぼー":1,"わらわないすうがくしゃ":1,"わすれがち":1,"わっし":1,"わーきんぐがーる":1,"わんえいとぷろもーしょん":1,"わけない":1,"わたるえーけーえーろく":1,"わいつーけい":1,"わいやれすほーす":1,"わいせい":1,"わがなはねろ":1,"わぎ":1,"わかなまい":1,"わかばやしげんぞう":1,"わかやまけんみんぶんかかいかん":1,"わうけいさお":1,"わぎゅうよたくしょうほう":1,"わたなべかずたみ":1,"わいどびゅーしなの":1,"わきげがもじゃんぼ":1,"わかとう":1,"わらびざ":1,"わんわんくるーず":1,"わかめさん":1,"わたしせん":1,"わぶか":1,"わらすぼ":1,"わーくきゃんぷ":1,"わいやれすねっとわーく":1,"わかやまちほうさいばんしょ":1,"わかこま":1,"わさいけんてい":1,"わたなべたけゆき":1,"わしのす":1,"わんでぃっしゅか":1,"わーるどわいどうぇっぶ":1,"わかまつく":1,"わたなべれいか":1,"わかばやしつとむ":1,"わたしのなにがいけないの":1,"わこーるほーるでぃんぐす":1,"わすれえぬ":1,"わかのさと":1,"わたなべありさ":1,"わたなべすみこ":1,"わもの":1,"わんがんみっどないと":1,"わたしががんだむだ":1,"わかものろん":1,"わいやーど":1,"わーゔる":1,"わらうくも":1,"わりふる":1,"わんしょう":1,"わたしのみらいのだんなさま":1,"わんぽう":1,"わかやまぼくすい":1,"わーぷまん":1,"わずひこ":1,"わたなべとみお":1,"わろかいなまほうそうぬし":1,"わんたっち":1,"わんないと":1,"わのうちちょう":1,"わじまし":1,"わっつーしぞんび":1,"わかものじりつじゅく":1,"わたりあう":1,"わたなべあすか":1,"わんふー":1,"わんなうと":1,"わかひるめのみこと":1,"わたなべやすひろ":1,"わばさみ":1,"わんぱん":1,"わがちょう":1,"わたしのほすとちゃんしちにんのほすと":1,"わたなべ":1,"わけあい":1,"わいるだねす":1,"わたしさつじんじけん":1,"わーきんぐどきゅめんと":1,"わがほう":1,"われながら":1,"わびね":1,"わかばやしすと":1,"わかいちこうじ":1,"わたなべしきぬかよろこびしすてむ":1,"わりむぎ":1,"わんさいどげーむ":1,"わけへだて":1,"わびる":1,"わくいせつお":1,"わしみゆーこ":1,"わかりづらい":1,"わたしはあなたをたべてやる":1,"わす":1,"わかみやはちまんぐう":1,"わーくぶーつ":1,"わがんあいご":1,"わんらいんだいやぐらむ":1,"わおすてき":1,"わたなべひでき":1,"わるてるさむえる":1,"わせだせつりょうちゅうがっこうこうとうがっこう":1,"わか":1,"わいあれすでんわ":1,"わいるどらいす":1,"わせだだい":1,"わかつまたくはいびん":1,"わをかける":1,"わたなべがーるず":1,"わだなおこ":1,"わをかく":1,"わーるどえーす":1,"わかやまちょう":1,"わんだーあきゅーと":1,"わんだふるおぽちゅにてぃ":1,"わたぼこり":1,"わかいもとやす":1,"わたはるかさん":1,"わーるどさっかーだいじぇすと":1,"わたなべてつや":1,"わいがや":1,"わくいゆう":1,"わたるもののとだえたはし":1,"わんじる":1,"わりつけしょり":1,"われまどりろん":1,"わさんぼんとう":1,"わきどうぶつえん":1,"わりびきさーびす":1,"わたるせけんはおにばかり":1,"わんころもち":1,"わからなくなってきました":1,"わんちゃんかっこいぬ":1,"わいず":1,"わんぐぁん":1,"わしんとんでぃーしー":1,"わたなべどおりえき":1,"わいどえっくすじーえー":1,"わたがわまなみ":1,"わたなべあけお":1,"わだたくま":1,"わこむ":1,"わんざありあけべいもーる":1,"わいの":1,"わんがんどうろ":1,"わづかちょう":1,"わらびのり":1,"わかやまけんだいさんく":1,"わかさゆり":1,"わかぎり":1,"わししょうひん":1,"わらたーす":1,"わちのがわきゃんぷ":1,"わきさわみほ":1,"わかやまげんぞう":1,"わいえむにーいちごーいち":1,"わたしたち":1,"わるきゅーれのぼうけん":1,"わいじゅ":1,"わしたにはな":1,"わたなべゆほ":1,"わるじゃれ":1,"わかやまあやか":1,"わるのり":1,"わたづみじんじゃ":1,"わだまゆみ":1,"わんはーふ":1,"わらきん":1,"わしづ":1,"わーなーほーむびでお":1,"わいるどかーどしょうめいしょ":1,"わかいころ":1,"わとそんかすみ":1,"わたなべとしゆき":1,"わりに":1,"わりばしぴー":1,"わにむ":1,"わいるどふらわー":1,"わんうえいびん":1,"わかやまけんりつひだかこうとうがっこう":1,"わじょう":1,"わすくある":1,"わかきひのおもいで":1,"わかやなぎちょう":1,"わかみやおおじ":1,"わーくす":1,"わんふろあ":1,"わいやれすらん":1,"わーきんぐおーぷにんぐぱろ":1,"わたつきしまい":1,"わらじや":1,"わんぷーあおばと":1,"わたぬきだいすけ":1,"わんわんわーるど":1,"わかばだいえき":1,"わんがんきき":1,"わーお":1,"わだ":1,"わんぐー":1,"わこでりか":1,"わいんさかば":1,"わいずまんはかせ":1,"わうふらった":1,"わーるどはやぶさ":1,"わにぶっくす":1,"わどえき":1,"わんだーふぉーげる":1,"わいざつ":1,"わたしめだちたい":1,"わたりあけし":1,"わかくさちょう":1,"わだん":1,"わかおゆう":1,"わけめ":1,"わたしとどくしょ":1,"わだた":1,"わだせいじ":1,"わかなよしはる":1,"わたらいしんとう":1,"われわれはぼうでたたかうしかない":1,"わたなべみりあ":1,"わるたーふぉんしぇーんこっぷ":1,"わかけほんせいいんこ":1,"わかるいこーるできるじゃない":1,"わめきごえ":1,"わらいほとけ":1,"わきでら":1,"わっく":1,"わだあきこ":1,"わかなたくま":1,"わたながし":1,"わしざきいじょうこいびとみまん":1,"わらびし":1,"われいしん":1,"わたなべふらわー":1,"わり":1,"わきのはまかいがんどおり":1,"わかどり":1,"わるつふぉーありあ":1,"わせだだいがくこうとうがくいん":1,"わっとけい":1,"わーるどえんたーぷらいず":1,"わそう":1,"わいずぷらんにんぐ":1,"わっかないちほうきしょうだい":1,"わたっかわ":1,"わじゅつ":1,"わかまつじま":1,"わきやまごう":1,"わっかないこうえん":1,"わがこへ":1,"わっさわさ":1,"わたくしどあらです":1,"わっきーかいやま":1,"わだつみちひろ":1,"わたなべきんいち":1,"わがしてん":1,"わーるどいずまいん":1,"わんがんきょうりょくかいぎ":1,"わかつきこういちろう":1,"わかやましりつわかやましょうぎょうこうとうがっこう":1,"わーるどばざーる":1,"わとそん":1,"わかしまづけん":1,"わくわくせいかつしえんねっと":1,"わすれさる":1,"わたしがすきならすきっていって":1,"わくらわ":1,"わらういぬのたいよう":1,"わせだほうしえん":1,"わくいこーぽれーしょん":1,"わななく":1,"わくわくせぶん":1,"わたちゃんぬ":1,"わかつ":1,"わたなべかなこ":1,"わたなべぱこ":1,"わるあがき":1,"わんら":1,"わんだーがーる":1,"わふうすぱげてぃ":1,"わかばやしけんじ":1,"わくせいべんしねえさん":1,"われしらず":1,"わいんぐらす":1,"わいずしゅっぱん":1,"わーなーまいかるしねまず":1,"わざとだよついだよ":1,"わーきんぐにきのえんどかーど":1,"わたなべしょうこ":1,"わかいりこん":1,"わんぽっとごうせい":1,"わたしをあいしたすぱい":1,"わっふるがすきなあっくん":1,"わっぺん":1,"わかきちょうにし":1,"わじぇろ":1,"わたりのうた":1,"わかつきゆみ":1,"わいゆー":1,"わかじししょう":1,"わたなべれいこ":1,"わかおらいでん":1,"わたなべみずき":1,"わーるどはいふきぼう":1,"わきあかり":1,"わいえすふらいとしみゅれーたー":1,"わくらば":1,"わんだーふぁんぐ":1,"われから":1,"わけありげ":1,"わようがくえん":1,"わばり":1,"わこうぷろだくしょん":1,"わてつ":1,"わこうこうとうがっこう":1,"わかりきる":1,"わぶるまほうとしょかん":1,"わたしのためならしはかたない":1,"わーぷあ":1,"わゆた":1,"わたせまゆ":1,"わんぱく":1,"わかまつこうじ":1,"わかばまーく":1,"わかーた":1,"わうわう":1,"わへいきょうてい":1,"わものいんりょうのひと":1,"わかいあつこ":1,"わるいたいさよん":1,"わーげん":1,"わいどれじゃー":1,"わっかないしょうこうかいぎしょ":1,"わいるどそるじゃー":1,"わうりんか":1,"わたせじねずみ":1,"わいけいけいえーぴー":1,"わかやませんきょく":1,"わたなべかずひと":1,"わけてみた":1,"わかやまけんせんきょく":1,"わんわんかつやくこひなたむそう":1,"わしだまさかず":1,"わなー":1,"わがままふぁっしょんがーるずもーど":1,"わしみみずく":1,"わんらんく":1,"わたっくす":1,"わたなべみさこ":1,"わーるどおぶうぉーぷれーんず":1,"わった":1,"わきやよしはる":1,"わいなりー":1,"わらぶき":1,"わくしょっぷ":1,"わがたにはみどりなりき":1,"わいじろこうさてん":1,"わいおじさん":1,"わがやのれきし":1,"わるもの":1,"わんさいど":1,"わろぴー":1,"わたしじゃないわたしじゃないそれはわたしじゃないわたしじゃないんだ":1,"わがら":1,"わたりのじき":1,"わかばやしすぽーつ":1,"わうふらったー":1,"わるたん":1,"わむ":1,"わたべじゅん":1,"わーすれちゃったーよーー":1,"わかまつつとむ":1,"わるつぴー":1,"わたしのかれはぱいろっと":1,"わきさんがちょう":1,"わだこれまさ":1,"わかばだいきた":1,"わたしのきょうときみのゆめみるあした":1,"わいや":1,"わるいーじすたじあむ":1,"わくをつける":1,"わせいがく":1,"わたしども":1,"わきこな":1,"わいえすふーど":1,"わーすわいるどっとこむ":1,"わたしえふでさん":1,"わたりたかし":1,"わかさせん":1,"われなべにとじぶた":1,"わたなべなおみ":1,"わんまんあーみー":1,"わーるどはぴねす":1,"わどうがんねん":1,"わかとあきら":1,"わたなべおさみ":1,"わたしのめいばんこれくしょん":1,"わいら":1,"わりかえし":1,"わかやまばす":1,"わとそにあ":1,"わんかっぷ":1,"わたなべくるみ":1,"わたくしだ":1,"わたなべふみお":1,"わろんじん":1,"わせいめっし":1,"わせだだいがくしゃかいかがくぶ":1,"わかもとにせ":1,"わかりきった":1,"わかくさやま":1,"わいるどさいれんす":1,"わぐるま":1,"われあらしぞ":1,"わーきんぐほりでー":1,"わたなべようこ":1,"わらっていいとも":1,"わえいじてん":1,"わらわべ":1,"わかとの":1,"わたりけんたろう":1,"わんがんまきし":1,"わかむき":1,"わいやろん":1,"わんないとらぶ":1,"わおー":1,"わたしがおせわしてあげる":1,"わでぃるどぅ":1,"わーとほっぐ":1,"わんぴーすちゃんねる":1,"わきじ":1,"われはめしあなり":1,"わけいじゅく":1,"わたしのくとぅるふ":1,"わたしはひらさわすすむだぞひらさわゆいじゃないのはきゅう":1,"わかまつちょう":1,"わかたいしょう":1,"わたらせけいこくせん":1,"わーるどおーだー":1,"わんころべえ":1,"わかばやしただひろ":1,"われちゅうたいこく":1,"わらうかえる":1,"わたりあるく":1,"わいぷいん":1,"わーるどまっと":1,"わかいおさむ":1,"わーるどめでぃかるかーど":1,"わきにおく":1,"わるわるだんいっせいりぷじっこういいんかい":1,"わだすすむ":1,"わすれもの":1,"わぽ":1,"わかやまけんしゅっしん":1,"わたあめきせつぴー":1,"わーるどぱんくらすくりえいと":1,"わたしのあしながおじさん":1,"わたなべみさと":1,"わりあてがく":1,"わかやまかていさいばんしょ":1,"わきみうんてん":1,"わたなべきよし":1,"わいるびょう":1,"わいきょくほうどう":1,"わっけいん":1,"わたなべとう":1,"わらきあのよる":1,"わきみず":1,"わかみつてるひこのみこと":1,"わーるどれこーど":1,"わりびきうんちん":1,"わらって":1,"わがままこれくしょん":1,"わたなべけんぞう":1,"わずか":1,"わりびきりつ":1,"わりつぎ":1,"わたくしじしん":1,"わーなーまいかる":1,"わたす":1,"わんた":1,"わかばやしとしかず":1,"わーるどわいどぴー":1,"わいえむ":1,"わいせつご":1,"わかたかぐんだん":1,"わたてぃあら":1,"わしおよう":1,"わりかし":1,"わなみ":1,"わすれがたみ":1,"わんす":1,"わらぞうり":1,"わたなべりんたろう":1,"わひれ":1,"わこなおき":1,"わんにゃんわーるど":1,"わっはほーる":1,"わんだふるくえすと":1,"わせだだいがくこうとうしはんぶ":1,"わにまがじんしゃ":1,"わだらっこにせい":1,"わたなべみなよ":1,"わるい":1,"わたしまーめい":1,"わいるどだろぉ":1,"わがきみ":1,"わじら":1,"わりをくう":1,"わいわいわい":1,"わなっぷ":1,"わかいゆうき":1,"わたしってじゃすてぃす":1,"わりきれる":1,"わいだにっと":1,"わっはーぶは":1,"わしてどうぜず":1,"わかまつどおり":1,"わたあめ":1,"わかた":1,"わきかわかいり":1,"わたなべゆか":1,"わかぎみ":1,"われわれのじさくきべやしりーず":1,"わかみやじんじゃ":1,"わんぱくこぞう":1,"わたせせいぞう":1,"わたしはすごい":1,"わかさちょう":1,"わかさわだえき":1,"わいあーるぴーのびえき":1,"わかすぎぐるーぷ":1,"わんつー":1,"わかいものがしら":1,"わだみさき":1,"わかばん":1,"わかやまにく":1,"わかさたかはまえき":1,"わがえ":1,"わらいえ":1,"わんぴーすかいぞくむそう":1,"わいやれすまいく":1,"わかやまけんりつとういんちゅうがっこう":1,"わくせいかんこうこう":1,"わたりじゅうろう":1,"わすれなごはん":1,"わかちあう":1,"わたなべありな":1,"わたなべまさき":1,"わたなべまもる":1,"わする":1,"わしわし":1,"わせだだいがく":1,"わーるどぶろぐざっつらいと":1,"わがこころめいきょうしすいされどこのてはれっかのごとく":1,"わらがいあさみ":1,"われもわれも":1,"わきのだ":1,"わにまがじん":1,"わんうえい":1,"わるくいう":1,"わたなべとしみ":1,"わいやーそー":1,"わかやまたいかい":1,"わきみさきまち":1,"わしゃらじえすえす":1,"わいるどあーむずあどゔぁんすどさーど":1,"わたなべだいごろう":1,"わんぱーくこうち":1,"わたなべたつお":1,"わだぐんいち":1,"わかいもの":1,"わたりがわえき":1,"わじましんじ":1,"わっふるず":1,"わたふきかいがらむし":1,"わきげまじん":1,"わんこ":1,"わたせまき":1,"わかとしのかみ":1,"わだのぶかた":1,"わるつだいじゅうななばんとたんちょうおおいぬのわるつ":1,"わくてかのわく":1,"わーまめね":1,"わるあそび":1,"わぴーのひゃくねんしりーず":1,"わがはいはしげである":1,"わかくらかすみ":1,"わたなべまさゆき":1,"わしおすみはゆうしゃである":1,"わたなべゆうぞう":1,"わがねる":1,"わかどしより":1,"わんのーと":1,"わかもののげんせばなれ":1,"わんいんちぱんち":1,"わるいむし":1,"わいやげーじ":1,"わせだじゅく":1,"わたたにきよし":1,"わしだこやた":1,"わがまま":1,"わーるどめいとみらいのひかりこじいん":1,"わるぴーち":1,"わかやまさんく":1,"わんもないと":1,"わっぱー":1,"わらいころげる":1,"わじまひろし":1,"わかいぼんはやと":1,"わぎほう":1,"わけて":1,"わせいてきたんおんかい":1,"わりましてあて":1,"わたりどの":1,"わたなべゆうき":1,"わいまーるけんぽう":1,"わこうだいがく":1,"わるいついんてーる":1,"わふうきょくまつりにせんじゅう":1,"わりき":1,"わだきょう":1,"わたせゆう":1,"わりしたじ":1,"わころん":1,"わりもどす":1,"わだゆきのぶ":1,"わかえじょう":1,"わりのわるい":1,"わかやましりつわかやまこうとうがっこう":1,"わかさのくに":1,"わるふざけとうこう":1,"わさん":1,"わたかのじま":1,"わてぃー":1,"わいんでぃんぐろーど":1,"わりふ":1,"わーるどいずまん":1,"わるがき":1,"わんがんすきーやー":1,"わたくしもまた":1,"わぴこげんきよほう":1,"わずらわす":1,"わたらい":1,"わんだーすぴーど":1,"わんぴーすぎがんとばとる":1,"わらいもの":1,"わんはんどれっどあいどらごん":1,"わぶ":1,"わらっているばあいですよ":1,"わくわくさん":1,"わけのわかった":1,"わかやまきたこうこう":1,"わゆだんちょう":1,"わたし":1,"わげものや":1,"わくいかずお":1,"われぽん":1,"わんぷ":1,"わっふる":1,"わがもの":1,"わきどらむ":1,"わーるどすたー":1,"わんだーぶっく":1,"わーじぶ":1,"わたしをはなさないで":1,"わらわやみ":1,"わまんち":1,"わーむすえんたていめんと":1,"わたなべこのみ":1,"わたなべあん":1,"わっしょいまっど":1,"わたなべまさかず":1,"わかびと":1,"わだいづくり":1,"わかやまのはしもとえき":1,"わかだいしょう":1,"わたしのでばんをさがして":1,"わらわんひめ":1,"わたなべばしえき":1,"わたなべさちえ":1,"わきぐろさつまのみだまし":1,"わつじてつろうぶんかしょう":1,"わっくわっくりずむばんど":1,"わたべさとる":1,"わかとら":1,"わだしょう":1,"わけがわからないよ":1,"わけあって":1,"わたなべまき":1,"わたなべすじ":1,"わんりーほん":1,"わたりとう":1,"わたなべまさ":1,"わかまつともか":1,"わんもり":1,"わらびでとう":1,"わんまいるうぇあ":1,"わかばやしただし":1,"わいやーすとりっぱー":1,"わお":1,"わがてきはわれにあり":1,"わいやーぷらんつ":1,"わたしのさいこうのともだち":1,"わけありひん":1,"わくむすび":1,"わたりがらす":1,"わきばら":1,"わらわしたい":1,"わたくしども":1,"わいえすえー":1,"わたしのばらをはみなさい":1,"わぎゃんぱらだいす":1,"わいるどきゃっと":1,"わだたくや":1,"わどう":1,"わからし":1,"わかのほう":1,"わーどきょうかい":1,"わんだーらすと":1,"わろた":1,"わんだふるしょっと":1,"わきみこ":1,"わかものことば":1,"わかものがしら":1,"わーふぁりん":1,"わかまつちょうにし":1,"わりおかんぱにー":1,"わーくしぇあ":1,"わせだこうとうこうがっこう":1,"わびすけつばき":1,"わおきつねざる":1,"わたくしあて":1,"わらさいきょう":1,"わりまし":1,"わたしのあんねっと":1,"わんがん":1,"わさびずし":1,"わたなべかっこかめい":1,"わたせりお":1,"わせだしぶやぷらいべーとりみてっど":1,"わりだか":1,"わかたけちょう":1,"わかだいしょうのゆうゆうさんぽ":1,"わくせいたんさ":1,"わかばやしまさやす":1,"わおちぇんちぇん":1,"わたなべたかひろ":1,"わんわんらくしゃ":1,"わんがんふんそう":1,"わんわんわんじけん":1,"わがくに":1,"わがただちか":1,"わーるどわいどでぃべろっぱーずかんふぁれんす":1,"わたせつねひこ":1,"わたなべともこ":1,"わんたーれん":1,"わーけーしょん":1,"わりこみきごう":1,"わんたいむぱすわーどせいせいき":1,"わかず":1,"わかくわかずと":1,"わけべのきたなまろ":1,"わいどこんばーしょんれんず":1,"わるぢえ":1,"わーるずえんどうらおもてだんすほーるらばーず":1,"わたぬきたみすけ":1,"わたしはひらさわすすむだぞひらさわゆいじゃない":1,"わとら":1,"わたりをつける":1,"わかふじ":1,"わかいとけいだい":1,"わをんゐちこ":1,"わりこみつうわ":1,"わきたあかね":1,"わかまつこうすけ":1,"わらいのぶんかじんこうざ":1,"わしずえんまのとうはい":1,"わすれられないおくりもの":1,"わたなべまりな":1,"わぎゅう":1,"わかり":1,"わいこうこく":1,"わかばやしけんた":1,"わさえき":1,"わかいしゅ":1,"わいえむわいえいちねんまつかくだいすぺしゃる":1,"わらづか":1,"わいりえもん":1,"わせだいりょうせんもんがっこう":1,"わーるどますたーず":1,"わすれられない":1,"わへいこうさく":1,"わらびりんご":1,"われなべ":1,"わるがしこい":1,"わっくん":1,"わとそんいーえっくす":1,"わすれねなるみら":1,"わかてげいにん":1,"わかさいも":1,"わーずおぶざまいんど":1,"わらいこける":1,"わたしのこいはほっちきす":1,"わたしのなまえはきむさむすん":1,"わだかずひろ":1,"わかはまあきこ":1,"わたしはひとらーのひしょだった":1,"わるよい":1,"わかばりゅうや":1,"わちえき":1,"わかばやしかずひろ":1,"わきまえ":1,"わざわいをまねく":1,"わりあい":1,"わっしょい":1,"わがはいはしゅふである":1,"わこうしみんぶんかせんたー":1,"わたしのさいていのともだち":1,"わかやまけんぎかい":1,"わんくおくんとぅん":1,"わっとじ":1,"わびさび":1,"わざきた":1,"わごむ":1,"わいつ":1,"わこーる":1,"わんくまどうめい":1,"わきがあまい":1,"わかもとあおい":1,"わんすするー":1,"わかやまめいぶつ":1,"わだまさや":1,"わかなひかる":1,"わていしょく":1,"わりおすのーまうんてん":1,"わきげ":1,"わじまみき":1,"わきたおんせん":1,"わんちゃせんせい":1,"わたなべはるとも":1,"わいどしょーせんきょ":1,"わんまんかー":1,"わかげのいたり":1,"わらた":1,"わくせいかいはついいんかい":1,"わきあきこ":1,"わにえき":1,"わかやまふるさとたんじょうび":1,"わごう":1,"わいるどうおーたー":1,"わかものずき":1,"わりばしせんぼんうでならし":1,"わかばだいにし":1,"わかきもえ":1,"わむう":1,"わるいたずら":1,"わりいん":1,"わだこう":1,"わたなべひでかず":1,"わろん":1,"わぼく":1,"わーきんぐでぃれくとり":1,"わーどりーふ":1,"わんだーらんどなねざーらんど":1,"わたらせばし":1,"わーくすてーしょんけいしき":1,"わたなべよしまさ":1,"わきかた":1,"わっかないし":1,"わぶんえいやく":1,"わかやましみんかいかん":1,"わかつき":1,"わらびゆうぞう":1,"わだまさと":1,"わだこうたろう":1,"わたべゆうこ":1,"わいずびじょん":1,"わかやまてん":1,"わたしはうみ":1,"わーるどかっぷ":1,"わーるどくらぶちゃんぴおんふっとぼーる":1,"わいどえりあねっとわーく":1,"わーぷでいず":1,"わかきひ":1,"わかこまあくしょんくらぶ":1,"わるざれ":1,"わらえるほどたちがわるいかんこくのはなし":1,"わごんしゃ":1,"わりだしまち":1,"わかきぶんごう":1,"わかさえき":1,"わくたん":1,"わいるどばんち":1,"わざび":1,"わーるわいく":1,"わたなべなつみ":1,"わるいおこない":1,"わかせんにん":1,"わたなべこうた":1,"わーきんぐどっぐ":1,"わたしもみんなとおなじえがおのいちいんです":1,"わいやれすかめら":1,"われはかげしんなるわれ":1,"わたなべえいじ":1,"わりだす":1,"わつきるみ":1,"わらいぞめ":1,"わかたべけんいち":1,"わかやまとねこのみこ":1,"わがままなながれぼし":1,"わぶろー":1,"わたなべたけお":1,"わんこいんばす":1,"わくせいかがく":1,"わんくりっくさいよう":1,"わかしまづ":1,"わふわふ":1,"わたなべひかる":1,"わいな":1,"わかや":1,"わにあし":1,"わらちょう":1,"わかばやしれいや":1,"わんるーむ":1,"わたなべたけし":1,"わぴーのこうれいぎょうじ":1,"わしんとんかーねぎーきょうかい":1,"わいやーふれーむ":1,"わきゅう":1,"わかばやししん":1,"わになっておどろう":1,"わっしー":1,"わかちがき":1,"わたしひますぎてさーせん":1,"わたなべすすむ":1,"わいどえふえむ":1,"わんぱくなかま":1,"わんさかむすめ":1,"わほん":1,"わーるどきねんほーる":1,"わしきりょうり":1,"わたしとはてなとのであい":1,"わいち":1,"わいあーむ":1,"わたしとかいじんじゃないしー":1,"わだいさく":1,"わくいけん":1,"わんおん":1,"わかばすてーくす":1,"わくいりょう":1,"わんぼ":1,"わかやまこうせん":1,"わーくはうす":1,"わらってたいんだ":1,"わだかずひと":1,"わたなべしほり":1,"わふうびーじーえむ":1,"わたなべちゅうめい":1,"わりぐりいし":1,"わだめぐみ":1,"わかばやしともか":1,"わきあげる":1,"わらやこうじん":1,"わなげ":1,"わたしだすわ":1,"わたなべりょうこ":1,"わかやまけんりつとういんこうとうがっこう":1,"わりとどうでもいい":1,"わかもとだいすけ":1,"わたなべひでつな":1,"わきまさし":1,"わざとらしいひと":1,"わんせこんどとらんざむ":1,"わかみやまち":1,"わるだくみ":1,"わいずえっぐ":1,"わいけいけい":1,"わりびきりょうきん":1,"わかつきさな":1,"わっくす":1,"わくらゆいな":1,"わしのみやじんじゃ":1,"わせがせえんげいじょう":1,"わりほぐす":1,"わがちゃ":1,"わかやまけんちじ":1,"わあああむーどかよう":1,"わだともき":1,"わくらまち":1,"わーくすてーしょんこうげん":1,"わさんか":1,"わだそうたろう":1,"わだよういち":1,"わしんじょうやく":1,"わかばがーるず":1,"わしず":1,"わがつまみわこ":1,"わんぱす":1,"わしょ":1,"わかいうち":1,"わるきゅーれ":1,"わたなべちえこ":1,"わたらせがわ":1,"わきたけいこ":1,"わかみやしょうがっこう":1,"わかりにくい":1,"わたなべけいじ":1,"わっちさん":1,"わかひさだんち":1,"わらがいりょうた":1,"わたなべさおり":1,"わらうけいかん":1,"わりおしっぷ":1,"わんげつ":1,"わたなべこうぞう":1,"わきむらはるお":1,"わっしょいしょうぐん":1,"わかくわみどり":1,"わーど":1,"わくたく":1,"わたしはねこすとーかー":1,"わっとざふぁっく":1,"わんこぴーあっといぬひろ":1,"わかきすいせいのしょうぞう":1,"わらしべようじょ":1,"わぎも":1,"わーるどこんばっとりーぐ":1,"わでぃらむほごちいき":1,"わしだきよかず":1,"わんぴーべりーまっち":1,"わきどうが":1,"わせださがちゅうがっこう":1,"わんぼっくすかー":1,"わっはかみがた":1,"わぬこ":1,"わくわくくん":1,"わいじぇいぴーおぶざいやーぜろきゅう":1,"われただたるをしる":1,"わたなべあつしのたてものたんほう":1,"わいんりすと":1,"わたなべたかお":1,"わーるどこん":1,"わきよししげ":1,"わんうぇーびん":1,"わりきれない":1,"わふうねこ":1,"わたしがしんはんにん":1,"わたなべひろし":1,"わしんとんじょうやく":1,"わいりーきち":1,"わらう":1,"わたなべたえこ":1,"わたなべまち":1,"わにら":1,"わりお":1,"わたべあきと":1,"わらぴー":1,"わいだん":1,"わりましうんちん":1,"わるさわぎ":1,"わかものたち":1,"わたしぶね":1,"わかばじゅうきゅう":1,"わーるぷーる":1,"わず":1,"わーるどしりーずおぶぽーかー":1,"わるじえ":1,"わざと":1,"わるぐち":1,"わじきおんせん":1,"わだたいすけ":1,"わたしはがくちょうです":1,"わたなべまさじ":1,"わくらおんせんえき":1,"わすれろびーむ":1,"わるびある":1,"わたしたちはずっとでしょう":1,"わるさーにせん":1,"わがものにする":1,"わど":1,"わいぷあうと":1,"わたしはうたがへた":1,"わかきちょう":1,"わいまーるきょうわせい":1,"わこふぁーす":1,"わがよのはる":1,"わたりがわすいけい":1,"わくせいだいかいじゅうねがどん":1,"わたべたけし":1,"わたなべまゆこ":1,"わきちょう":1,"わるしゃわ":1,"わたなべみつる":1,"わりぼしだいこん":1,"わかばかいようちえん":1,"わりびきかかく":1,"わんだふるがーるず":1,"わがはい":1,"わーぷろ":1,"わーきんぐめもりー":1,"わたなべだいすけ":1,"わだいさみ":1,"わたどの":1,"わかばやしまさと":1,"わくてかなまほうそうぬし":1,"わんだらぴー":1,"わんわんお":1,"わたいこ":1,"わたりぞめ":1,"わたなべやすし":1,"わーかー":1,"わーぷろそふと":1,"わたみのかいご":1,"わたぬきばんり":1,"わんだーふりっく":1,"わたなりどうてい":1,"わかいはじめ":1,"わかめはぎせいになったのだ":1,"わかばみらい":1,"わいほん":1,"わんもあえくすとらすてーじ":1,"わたなべよしとも":1,"わだゆたか":1,"わきみこのみそあせぺろぺろ":1,"わかれでる":1,"わかひな":1,"わて":1,"わかつきだんち":1,"わざおぎ":1,"わるぼう":1,"わせだれぶるす":1,"わけのわからないもの":1,"わかまつ":1,"わっはーぶ":1,"わんにゃふるらいふ":1,"わほうたいのかい":1,"わぶゆー":1,"わたなべさん":1,"わかはぎ":1,"わんぴー":1,"わらってこらえて":1,"わいあいえる":1,"わっと":1,"わこだぬき":1,"わかばやしまな":1,"わりこ":1,"わたなべただよ":1,"わんぼっくす":1,"わたしにできること":1,"わしょくや":1,"わりご":1,"わたなべさかえ":1,"わだなっと":1,"わたしがれんあいできないりゆう":1,"わたしをりょかんにつれてって":1,"わきでる":1,"わだひろこ":1,"わふどとう":1,"わらいだけ":1,"わんだーみんつ":1,"わあっ":1,"わんせっと":1,"わらいかける":1,"わたなべたく":1,"わーぷすたー":1,"わかすかいひんこうえん":1,"わきたつ":1,"わたなべみき":1,"わたなべひろふみ":1,"わせだ":1,"わだけん":1,"わかばやしなみこ":1,"わくわくれんたかー":1,"わだあやお":1,"わらびー":1,"わわわわーにんぐ":1,"わりぐり":1,"わらってるばあいですよ":1,"わかそぞく":1,"わきななか":1,"われもこう":1,"わぐり":1,"わんそくどうぶつ":1,"わいやろーぷ":1,"わっち":1,"われがーな":1,"わんだーすわん":1,"われわれだん":1,"わんこていこくちょっかつかんりほうそうち":1,"わたなべたけのぶ":1,"わきばしら":1,"わかやまかれーじけん":1,"わしんとんほてる":1,"わーるどぼくしんぐだーくそうる":1,"わたなべせいいち":1,"わきがみえき":1,"わいろかーと":1,"わりゅうすたー":1,"わるいことしたとりー":1,"わんぴーすのかんれんしょうひんいちらん":1,"わんだふるはーつ":1,"わいせつざい":1,"わごんせーる":1,"わんみにっつししょくき":1,"わらびてとう":1,"わいもでむ":1,"わたりちょう":1,"わかさけいいち":1,"わんすてっぷばす":1,"わたしのひび":1,"わいしょうか":1,"わちゃわちゃにょにゃにゅにょにゃぷにゃぷょぴぱらぺにゃぷきゃぴゅりゃぺぴょ":1,"わきたひろゆき":1,"わしざきたけし":1,"わきたしげる":1,"わたなべぽん":1,"わかさじんぐうじ":1,"わいせんべるく":1,"わりつけじゅんばん":1,"わけがある":1,"わっせ":1,"わんすいんぐしただけでごてんはいった":1,"わたなべかずふみ":1,"わいやれすまうす":1,"わかまつぷろ":1,"わごんさん":1,"わたなべくみこ":1,"わたしねこみみもえこです":1,"わーるどくらす":1,"わかまつゆみ":1,"わんだーえでぃー":1,"わーあれをみろぉ":1,"わそらん":1,"わたなべけんじ":1,"わんぴーすぎがんとばとるつーしんせかい":1,"わかんいがく":1,"わりふり":1,"わんやんてくない":1,"わーるどほりでぃ":1,"わたすげ":1,"わいせつぶんしょ":1,"わかしょうよう":1,"わえいじしょ":1,"わーろっく":1,"わみょうるいじゅしょう":1,"わたしはかわないがうれてほしいものだ":1,"わーぷざら":1,"わだちゃん":1,"わーくしぇありんぐ":1,"わかやまどくかれーじけん":1,"わたりだひがしちょう":1,"わしづかけいいちろう":1,"わーくじゃむ":1,"わこちーず":1,"わいろ":1,"わしおたかし":1,"わへいごうい":1,"わんこーるわーかー":1,"わかみやひろふみ":1,"わさびくん":1,"わかものぐみ":1,"わらんと":1,"わたなべちさと":1,"わかばやしおさむ":1,"わかみやきよし":1,"わらむしろ":1,"わいえむおー":1,"われかえる":1,"わいなーと":1,"わだよしもり":1,"わいはおおさかでくみちょうやっとるけんぶーや":1,"わつき":1,"わらいかもめ":1,"わのり":1,"わたなべやすゆき":1,"わんあうときのこ":1,"わだじょうじ":1,"わがそこく":1,"わだらじお":1,"わかれぎわ":1,"わんにゃぶ":1,"わんだーぱひゅーむ":1,"わたなべゆきひろ":1,"わんげるけいすう":1,"わたなべひとみ":1,"わかどりどん":1,"わたつみさんいん":1,"わかやまけんたいかい":1,"わけのわからないひと":1,"わーくすてーしょんどくりつせぐめんときおくいき":1,"わーふぇにっくす":1,"わりつける":1,"わーくすてーしょんじょうたいりすと":1,"わだみさきとうだい":1,"わんぱい":1,"わたりそうすけ":1,"わーるどくろすぴーぶいぴー":1,"わのごおう":1,"わにえそ":1,"わんねす":1,"わづましっかいや":1,"わきのした":1,"わぼうちょう":1,"わこうしえき":1,"わいえーじーあにめらぼ":1,"わたしのあおぞら":1,"わるぎりあ":1,"わんだーがーるす":1,"わたしのせんそうはんざい":1,"わたなべようすけ":1,"わたしたちのたむらくん":1,"わだかおる":1,"わだごういち":1,"わいるどらんぴー":1,"わざうた":1,"わしずいわお":1,"わんがい":1,"わらかんぶろぐ":1,"われわれのぎょうかいではほめことばです":1,"わかぐりえき":1,"わるずいりょう":1,"わたべのおいなりさん":1,"わたなべまな":1,"わーどすう":1,"わたなべこめでぃすくーる":1,"わいんばれー":1,"わりおすたじあむ":1,"わきづけ":1,"わらがみさまはとつぜんに":1,"わかてとっぷじょゆう":1,"わいるだーずばたふらいふぃっしゅ":1,"わらいたけ":1,"わんちゃんす":1,"わかくさ":1,"わさびどら":1,"わたしのあたまのなかのけしごむ":1,"わたなべこうき":1,"わかたべかつひこ":1,"わこうふーず":1,"わってはいる":1,"わいるどあーむずせかんどいぐにっしょん":1,"わしづえき":1,"わかやまだいがくまええき":1,"わっは":1,"わたなかむらさんはむかしからうたがおじょうずですよ":1,"わかおうじみみお":1,"われわれのぎょうかいでもごうもんです":1,"わんわん":1,"われわれのぎょうかいではごちそうです":1,"わっきゅん":1,"わーん":1,"わーくしぇりんぐ":1,"わるてるがるがーの":1,"わぁひどいかりぃ":1,"わすれえぬひとびと":1,"わかうつぼ":1,"わたべけん":1,"わきど":1,"わらえるがぞうをはろうぜ":1,"わたなべこうへい":1,"わらがみ":1,"わたなべせいさくじょ":1,"わんすりーしゅ":1,"わたなべまゆ":1,"われんしゅたいん":1,"わだへいすけ":1,"わたりぼうこう":1,"わりまえ":1,"わかやまけんちじせん":1,"わと":1,"わかれわかれになる":1,"わかなみなみどおり":1,"わんくりさぎしじょうほう":1,"わにせんにん":1,"わーくしーと":1,"わせん":1,"わだむしぞう":1,"わいるどふらっぱー":1,"わかおくさま":1,"わたしたちのきょうかしょ":1,"わかれじも":1,"わんこいぬ":1,"わかばやしこうき":1,"わざのでぱーと":1,"わいつーけー":1,"わたなべしょうた":1,"わざらいしずや":1,"わけあり":1,"わじろえき":1,"わたしのあいわたしのそばに":1,"わたなべじゅんいちぶんがくかん":1,"わいどすかじー":1,"わたぼく":1,"わがなはしょうがくせい":1,"わだひでき":1,"わんすてっぷずつ":1,"わにっぱい":1,"わたゆき":1,"わりざん":1,"わたくしまんが":1,"わようじょしだいがく":1,"わかばやしみお":1,"わへいかいだん":1,"わせいかがわ":1,"わんせぐでか":1,"わかさすたじあむきょうと":1,"わんるーむまんしょん":1,"わぎな":1,"わんこにくちづけ":1,"わきみこれいむ":1,"わたはしやすみ":1,"わかつきれいじろう":1,"わくせい":1,"わりこう":1,"わがみをうらむ":1,"わけのきよまろ":1,"わっくすえすてる":1,"わがらし":1,"わんさがーる":1,"わるきゅりあ":1,"わだらっこ":1,"わちのぼる":1,"わんぽ":1,"わほう":1,"わけもなく":1,"われかんせず":1,"わーきんぐらんち":1,"わんつーすりー":1,"わしゅう":1,"わきによる":1,"わかばやしちょう":1,"わたぬきしゅん":1,"わーれっと":1,"わじゅつさいど":1,"わかかえで":1,"わこくちょう":1,"わびうた":1,"わんらいてぃんぐしすてむ":1,"わたりだしんちょう":1,"わかのはなかんじ":1,"わっちみー":1,"わたしたちのいきるこのりあるこそがまかいなんだ":1,"わざあり":1,"わいりー":1,"わんわんすたいる":1,"わかみゆき":1,"わきやまたまみ":1,"わがはいはげーむである":1,"わんどおぶふぉーちゅん":1,"わるいくせ":1,"わーるど":1,"わかしゅどう":1,"わだしんいちろう":1,"わかまらぴー":1,"わたみふぁーむ":1,"わたなべとしお":1,"わいうぇすと":1,"わいやれす":1,"わるびれずに":1,"わんだーかふぇ":1,"わしおなおひろ":1,"わい":1,"わかいこづえ":1,"わだせいみつしけんかぶしきかいしゃ":1,"わたなべばし":1,"わかやまあきら":1,"わかな":1,"わらわれたこ":1,"わるずれ":1,"わすれないでね":1,"わんまじん":1,"わにのこ":1,"わね":1,"わしずむ":1,"わだこーぽれーしょん":1,"わんふぇす":1,"わかたけしょう":1,"わかばやしなおみ":1,"わらそく":1,"わくたまくん":1,"わんまんこんとろーる":1,"わかじに":1,"わりかんがち":1,"わたなべやすのり":1,"わただえき":1,"わたしはしゃどう":1,"わさ":1,"わいどどあ":1,"わくおわったらばいちい":1,"わんくりっくさぎ":1,"わたなべめそっど":1,"わひとども":1,"わたなべまりえ":1,"わんだらー":1,"わだみさきえき":1,"わぼくのししゃ":1,"わせだどおり":1,"わあるどだうんたうん":1,"わかまつむさし":1,"わきさかしげかず":1,"わんだふるでいず":1,"わきさかじゅいち":1,"わたりろうか":1,"わーすいちまるきゅうに":1,"わかのはなまさる":1,"われらのだん":1,"わかもののくるまばなれ":1,"わいちゃん":1,"わびしい":1,"わかえいわたえき":1,"わがわみゆう":1,"わっぱ":1,"わいやーどまりおねっと":1,"わしずこぷたー":1,"わたなべたすく":1,"わだつみかい":1,"わたなべゆうこ":1,"わんだふる":1,"わたなべあきら":1,"わかすぎきみのり":1,"わたせゆうた":1,"わなんばら":1,"わしおまちこ":1,"わたしがたり":1,"わたせ":1,"わなま":1,"わたなべひとし":1,"わらんとさい":1,"わかまつだいし":1,"わだよしえ":1,"わんないとじんろう":1,"わーるどいずあみん":1,"わたなべひでみ":1,"わどるどぅ":1,"わたなべさだお":1,"わじまぬりだいゔぉー":1,"わたくしなどには":1,"わかものどれいじだい":1,"わりかんまけ":1,"わにとかげぎすもく":1,"わかきりーだー":1,"わいしん":1,"わかみやはちまんぐうしゃ":1,"わたなべのぶたか":1,"わかやまけんりつせいりんこうとうがっこう":1,"わたくしぎ":1,"わるいことはいわない":1,"わしおはるか":1,"わーるどにゅーすあわー":1,"わーるどこむ":1,"わーくぷれーすめんと":1,"わしんとんほてるちぇーん":1,"わさわさ":1,"わんじぇー":1,"わっきゃない":1,"わくせいいんぱくとをすくえ":1,"わざっか":1,"わかきおうじとおうじょ":1,"わたしがいきるはだ":1,"わだえり":1,"わたしとしごとどっちがだいじなの":1,"わたなべたくみ":1,"わたなべあや":1,"わいじいけい":1,"わんくーるあいどる":1,"わかばやしごう":1,"わっさん":1,"わんあうと":1,"わーくぐるーぷ":1,"わいえすぴー":1,"わかばやしく":1,"わーく":1,"わなりょう":1,"わかやまし":1,"わこつけもの":1,"わーすごーい":1,"わむざとはる":1,"わがさ":1,"わるいーじぴんぼーる":1,"わかえぐん":1,"わんだばすたいる":1,"わりたやすひこ":1,"わんわんろーど":1,"われとおもわんもの":1,"わくがたあんてな":1,"わけし":1,"わらびえき":1,"わきく":1,"わきもと":1,"わーるどばかくらしっく":1,"わーるどぼーかろいどずたーこいずふぇすてぃばるつー":1,"わらうなほれる":1,"わかむらまゆみ":1,"わんにゃー":1,"わたしがあやのよめ":1,"わかめのかい":1,"われぜんどう":1,"わたちゅー":1,"わにこうえん":1,"わーるどぼーかろいどずたーこいずふぇすてぃばる":1,"わかいみどり":1,"わたしのこいはほいっする":1,"わさなか":1,"わりがき":1,"わたるせけんにおにはない":1,"わかめちゃん":1,"わなたべなおみ":1,"わたがしやさんふわり":1,"わたなべひでまろ":1,"わかだんな":1,"わかき":1,"わいるどべーすぼーらーず":1,"わつうぶんべん":1,"わたしといううんめいについて":1,"わだしんじ":1,"われら":1,"わたぬきまち":1,"わかやまびっぐほえーる":1,"わっする":1,"わになし":1,"わがやのいぬはせかいいち":1,"わどうくろや":1,"わたなべなおき":1,"わたなべたくま":1,"わりびきぶあい":1,"わんさ":1,"われわれのこりぶり":1,"わるいなみだ":1,"わぬ":1,"わかやぐ":1,"わだたかし":1,"わしたにいづみ":1,"わけしりがお":1,"わたしのためにつくりなさい":1,"わも":1,"わせだせつりょうちゅうがっこう":1,"わんだーすわんからー":1,"わいどこんばーたー":1,"わかんない":1,"わたくしたち":1,"わかしおぎんこう":1,"わぁきたない":1,"わだかずこ":1,"わだやまえき":1,"われぼめ":1,"わらでたばねてもおとこはおとこ":1,"わだなおた":1,"わたなべゆき":1,"わかばまち":1,"わかみまち":1,"わに":1,"わたなべてつ":1,"わたなべすけさく":1,"わだじまちょう":1,"わこちょれぎ":1,"わくせいしゃも":1,"わかすぎりん":1,"わたなべとしこ":1,"わんふぁんめい":1,"わたみのたくしょく":1,"わらいなき":1,"わし":1,"わぎえ":1,"わっちー":1,"わんがんとらいある":1,"わきだす":1,"わかうど":1,"わたなべまほろ":1,"わかさまさし":1,"わかどりのえひふ":1,"わじましょうこうかいぎしょ":1,"わきでるるなさへのあいじょう":1,"わがし":1,"わりこみようきゅう":1,"わがゆうすけ":1,"わいけー":1,"わたなべゆみこ":1,"わーうるふ":1,"わだのひと":1,"わんりょくざた":1,"わーきんぐめもり":1,"わぶち":1,"わたりにふね":1,"わらしな":1,"わたなべひろき":1,"わくつとも":1,"わだやすひろ":1,"わしおれいな":1,"わくせいぴすたちお":1,"わぶる":1,"わんない":1,"わんとれーでぃんぐ":1,"わーるどいずおーるわん":1,"わたさく":1,"わるさ":1,"わくや":1,"わっしわっし":1,"わたなべめぐみ":1,"わじろがおか":1,"わいやれすじゃぱん":1,"わがっき":1,"わるいばしょ":1,"わかっているのにごめんね":1,"わーかほりっく":1,"わたなべはるか":1,"わにわわかってない":1,"わぁいのひと":1,"わらわらわら":1,"わたしょうふんか":1,"わーぷどらいぶ":1,"わげもの":1,"わかやましゅっしん":1,"わーきんぐ":1,"わたしやかをる":1,"わにをすででつかまえるほうほう":1,"わたりがに":1,"わーるどえんどどみねいたー":1,"わらわずぎらい":1,"わーくほりっく":1,"わんうえすと":1,"わっかないえき":1,"わしゅうそうほんざん":1,"わんぎりさぎ":1,"わいやー":1,"わんかっぷぴーりすぺくと":1,"わりおらんどあどばんす":1,"わしのみやえき":1,"わかものどれい":1,"わかしまただし":1,"わしょくさくら":1,"わかなしゅう":1,"わんだーうーまん":1,"わいやふれーむひょうげん":1,"わきじょうめん":1,"わがつまさんはおれのよめ":1,"わーすときす":1,"わりつけていさい":1,"わーぷしん":1,"わっちゃん":1,"わかものひはん":1,"わりきる":1,"わしんとん":1,"わだいこ":1,"わすれないでよ":1,"われいこうえん":1,"わーかーずゆにおん":1,"わらういぬのぼうけん":1,"わたりめりー":1,"わのこころによいしれろ":1,"わかぬけふたまたのおうじ":1,"わんわんたいむ":1,"わずらわせる":1,"わいぜっとえふあーるふぃふてぃーん":1,"わんこしょうねん":1,"わがかわ":1,"わたなべみちあき":1,"わらのいぬ":1,"わたなべたかし":1,"わかたべはるか":1,"われめがわ":1,"わいきゅーぶ":1,"わたしはおまえにこいしてんじゃぼけぇ":1,"わえ":1,"わんこていこく":1,"わたしにふかのうはない":1,"わへいく":1,"わくせいうっどすとっくふぁんきーほらーばんど":1,"わかもののてれびばなれ":1,"わけにはいかない":1,"わたなべえんたーていんめんと":1,"わたしたちのさんじゅうにじかんのとうそう":1,"わるに":1,"わぎゃんらんどつー":1,"わっちだいふ":1,"わかもののにんげんばなれ":1,"わからん":1,"わーるどえんど":1,"わーきんぐでぃすたんす":1,"わちゃーかっこわっちあうと":1,"わかざかり":1,"わけいる":1,"わじまこういち":1,"わたしはとらになりたい":1,"わたのは":1,"わいえすわい":1,"わらいがいちばん":1,"わきかえる":1,"わいるどすろー":1,"わんぴ":1,"わかたべまこと":1,"わいんでー":1,"わだかなえ":1,"わるふざけ":1,"わたなべあきよし":1,"わたしとだんしとししゅんきもうそうのかのじょたち":1,"わくでき":1,"わとじ":1,"わるめだち":1,"わいゔぁん":1,"わんきょくしりーず":1,"わさびしんし":1,"わしざきたけしのおうさまはたいくつじゃ":1,"わんるーむでぃすこ":1,"わるげ":1,"わかちあたえる":1,"わけやすい":1,"わたみたくしょく":1,"わすれたくないなつ":1,"わかさありたえき":1,"わかまつさとし":1,"わーるどおぶたんくす":1,"わだりょうかく":1,"わらいがお":1,"わたねこ":1,"わかむすび":1,"わりやす":1,"わたなべいっぺい":1,"わかさとくじ":1,"わたなべにさく":1,"わるこめ":1,"わきのう":1,"わるさーぴーさーてぃーえいと":1,"わたなべれな":1,"わせいえいご":1,"わきみ":1,"わんあんどおんりー":1,"わくふばんく":1,"わたなべかつあき":1,"わりおのもり":1,"わだひろき":1,"わくわくゆうかりんらんど":1,"わたなべのつな":1,"わたなべえりか":1,"わかとおおはし":1,"わいぱー":1,"わたべよしと":1,"わかやまこう":1,"わくさわりか":1,"わんまんうんてん":1,"わらえばいいとおもうよ":1,"わめい":1,"わたしのすきなしゃしん":1,"わたしはぶるーべりーぱい":1,"わけまえ":1,"わするなぐさ":1,"わいるどあーむずざふぉーすでとねいたー":1,"わかやまぼくすいしょう":1,"わからない":1,"わたなべはまこ":1,"わんせぐほうそう":1,"わびをいれる":1,"わがままふぁっしょんがーるずもーどよくばりせんげん":1,"わーるどあぱーと":1,"わがたいのたこるかさんのにちじょう":1,"わたなべもとじ":1,"わたしたちのしゅうまつ":1,"わこびあ":1,"わーくわーく":1,"わーなーえんたーていめんとじゃぱん":1,"わんまーに":1,"わらじをぬぐ":1,"わんぽいんとあどばいす":1,"わんたん":1,"わーくろーど":1,"わいやれすじゅうでん":1,"わりばし":1,"わたなべいたる":1,"わさきななみ":1,"わたしのとうほうめどれー":1,"わこうたちばなようちえん":1,"わらいをとる":1,"わーるどひーろーず":1,"わるきゅーれのでんせつ":1,"わかしろ":1,"わさみ":1,"わかめそーど":1,"わぐさんほいほい":1,"わいるど":1,"わんぱくおおむかしくむくむ":1,"わたくず":1,"わかぞのちょう":1,"わいちぇっく":1,"わーむわーるど":1,"わかすぎ":1,"わしのおたかつむ":1,"わだいをふる":1,"わくいまなぶ":1,"わらっていいともぞうかんごう":1,"わぶかがわ":1,"わせださがちゅうがっこうこうとうがっこう":1,"わかめだんす":1,"わがみをつねってひとのいたさをしれ":1,"わもんごきぶり":1,"わんだーこあ":1,"わんばおしゃん":1,"わんしーたー":1,"わへいこうしょう":1,"わいるどないつ":1,"わるものさん":1,"わかいしゅう":1,"われらようきなすぺらんかー":1,"わらづと":1,"わいぜろろくよんいちきゅうはちさん":1,"わーるどらぼ":1,"わさらー":1,"わだまさひろ":1,"わんこう":1,"わたなべあやの":1,"わせいぽっぷす":1,"わんはーふぴー":1,"わきてつ":1,"わしづなつえ":1,"わかさほんごうえき":1,"わりましりょうきん":1,"わいてぃーあっとねこちゅう":1,"わかさぎ":1,"わくふぁーすと":1,"われはねがうでんせつのあいどる":1,"わたしをどせいにつれてって":1,"わざとらしい":1,"わたしば":1,"わかすのふうしゃ":1,"わんせぐもばいる":1,"わどの":1,"わにぐち":1,"わかまつし":1,"わたりねのあ":1,"わっかない":1,"わただすすむ":1,"わきかわあすか":1,"わくわくあおいろしんこく":1,"わかまつつうしょう":1,"わるお":1,"わかちくけんせつ":1,"わーにんぐ":1,"わしんとんなしょなるず":1,"わだはまえき":1,"わかのすずや":1,"わだうら":1,"わいせんしょくたいあだむ":1,"わたなべまさたか":1,"わしらわっほいえんげいだん":1,"わづきのぶひろ":1,"わーるどにゅーす":1,"わかうかのめのみこと":1,"わたれたす":1,"わたたく":1,"わーい":1,"わたしのきらいなたんてい":1,"わらわれもの":1,"わらいめし":1,"わせだちえ":1,"わすれらんねえよ":1,"わっとあっとたけも":1,"わっせるまんはんのう":1,"わんだりんですてぃにー":1,"わかぎ":1,"わだつとむ":1,"わっふるわっふる":1,"わたなべぺこ":1,"わたなべまさと":1,"わたしをなかせてください":1,"わたなべしのぶ":1,"わきやくものがたり":1,"わわんこ":1,"わこと":1,"わたしはかいになりたい":1,"わんぱこ":1,"わらべまつり":1,"わこうちゅうがっこう":1,"わっともるてむ":1,"わがいをえたり":1,"わいるどじゃぱん":1,"わだじゅろう":1,"わしんとんし":1,"わせだえいと":1,"わたしのあいばはきょうぼうです":1,"わかいせず":1,"わらいじょうご":1,"わらをもすがる":1,"わだみのる":1,"わんだーがーるず":1,"わいるどがんまん":1,"わらやね":1,"わさてつろう":1,"わけよい":1,"わぬけやっこ":1,"わいおみんぐ":1,"わかばやしじょう":1,"わちゃかなどぅ":1,"わかまつたけし":1,"わいるどういんど":1,"われらろりーこんだ":1,"わんぴひめ":1,"わたしはあいどる":1,"わーるずえんどすーぱーのゔぁ":1,"わだいになる":1,"わにぶち":1,"わんこそば":1,"わーるどわーるどわーるど":1,"わずかなすきをねらっていくしかない":1,"わんやんあぐだ":1,"わくふ":1,"わたなべさちよ":1,"わたつみ":1,"わかばうぉーく":1,"わたくししょうせつ":1,"わしき":1,"わりいしおんせん":1,"わこめろん":1,"わんしぁおじん":1,"わざをみがく":1,"わさせきど":1,"わらばい":1,"わいといっしょにならないか":1,"わだれん":1,"わたつきのとよひめ":1,"わいど":1,"わがしめーかー":1,"わいんばー":1,"わだっちー":1,"わすれーるがん":1,"わかまついちまさ":1,"わかったー":1,"わんないとじぇらしーず":1,"わーなー":1,"わーなーみゅーじっく":1,"わーくすてーしょんきじゅつひょう":1,"わたなべまちこ":1,"わたみふーどしすてむず":1,"わがろうたしあくのはな":1,"わいご":1,"わんにゃーわーるど":1,"わたなべかずき":1,"わんちゃい":1,"わかざと":1,"わせだだいがくこうぎょうこうとうがっこう":1,"わいきき":1,"わんいーぜん":1,"わりぼし":1,"わらにゅーすぷらす":1,"わくせいうらない":1,"わかいぼん":1,"わーるどかっぷしんぱんいん":1,"わたなべくにひこ":1,"わたなべみさ":1,"わいえむにーにーぜろさん":1,"わにさぶろう":1,"わせだだいがくわかぐちげいじゅつがっこう":1,"わかやまけんりついかだいがく":1,"わかくみえる":1,"わだこうじ":1,"わんりるきす":1,"わごなー":1,"わたびきかつひこ":1,"わきこぼれる":1,"わたなべしゅうへい":1,"わくいのりお":1,"わだしげひろ":1,"わすれかける":1,"わいるどどっぐ":1,"わだくによし":1,"わたなべみつてる":1,"わったー":1,"わっとばうとまいすたー":1,"わけひろゆき":1,"わんすてっぷ":1,"わこうただやす":1,"わかくさなべ":1,"わいえすけー":1,"わりのいい":1,"わくらおんせん":1,"わだへーきょうじゅ":1,"わにばれえ":1,"わかれにのぞん":1,"わたなべしほ":1,"わかきたみき":1,"わーなーみゅーじっくじゃぱん":1,"わるぎ":1,"わ":1,"わひたろ":1,"わたなべぼくじょう":1,"わかもとやるお":1,"わたしはもつではないすーぱーもつだ":1,"わたなべてい":1,"わじままき":1,"わーぷろつうしん":1,"わらにもすがるおもいで":1,"わかやなぎぎゅう":1,"わかななかどおり":1,"わだよしひこ":1,"わすれられたしょうぞう":1,"わたなべじろう":1,"わいるどかーどもじ":1,"わかいときのくろうはこうてもせよ":1,"わたなべだい":1,"わーくすこーぽれーしょん":1,"わくいひであき":1,"わせだぶんがく":1,"わしょく":1,"わにりん":1,"わかづくり":1,"わんめーたー":1,"わりやすかん":1,"わいあんどこーいずでっどおああらいぶ":1,"わっかないしりつのしゃっぷかんりゅうすいぞくかん":1,"わいどなしょー":1,"わたべあつろう":1,"わすれおうぎ":1,"わもんあざらし":1,"わしょくさと":1,"わたもて":1,"わだや":1,"わーくふろー":1,"わんこいん":1,"わくとりせんそう":1,"わかれあらそう":1,"わかやぎりゅう":1,"われにもなく":1,"わかまつとしひで":1,"わんだね":1,"わんだーほー":1,"わたなべただし":1,"わーるどぽーたーず":1,"わかさま":1,"わらびのこう":1,"わずかなしんくろ":1,"わかりしころ":1,"わたなべともひろ":1,"わしずよしあき":1,"わたなべきょうじ":1,"わいるどらいふ":1,"わたなべまりあ":1,"わいんびねがー":1,"わーるどみゅーじっく":1,"わたなべもりあき":1,"わかさきけん":1,"わたぎぬ":1,"わたなべひろみ":1,"わたしがわたしであるために":1,"わじふどう":1,"わらえない":1,"わふうくっきー":1,"わしおうこう":1,"わきち":1,"わくせいこーねりあ":1,"わたなべゆかり":1,"わりびき":1,"わーどぷれす":1,"わぬけ":1,"わいしょう":1,"わいん":1,"わらえなかったらまけ":1,"わめく":1,"わこうだい":1,"わんかっぷぴー":1,"わこうちょう":1,"わげんせ":1,"わや":1,"わーるどわいど":1,"わたなべとしや":1,"わかいときのくろうはかってもせよ":1,"わんようあんてな":1,"われおもうゆえにわれあり":1,"わたなべえりー":1,"わいるどあーむずくろすふぁいあ":1,"わようせっちゅう":1,"わんでるんぐ":1,"わりもどしきん":1,"わたしはしんご":1,"わのつ":1,"わたなべかねお":1,"わたしはしもだった":1,"わたなべまゆみ":1,"わかやまどくぶつかれーじけん":1,"わたしなんばわーん":1,"わにわにものがたり":1,"わきもとあやの":1,"わたなべけんさく":1,"わせだだいがっこうとうがくいんちゅうがくぶ":1,"わらいとばす":1,"わようちゅう":1,"わいるどさんにんむすめ":1,"わきやよしすけ":1,"わしんとんからー":1,"わけるくん":1,"わだつみ":1,"わかばのひと":1,"わぴち":1,"わーどあーと":1,"わけもつ":1,"わたなべのぞみ":1,"わざのたびびと":1,"わだみ":1,"わるざえもん":1,"わしくり":1,"わさんぼんわがしやてんまつき":1,"わだひろしとまひなすたーず":1,"わたぬきひびき":1,"わーじんとん":1,"わくせいすたーらいとーただいまのうたー":1,"わたりま":1,"わける":1,"わかさぎづり":1,"わだあきら":1,"わざぽん":1,"わんだーえっぐ":1,"わたりかずひさ":1,"われいちょう":1,"わかやまけんりつわかやまこうとうがっこう":1,"わせい":1,"わかんこんこうぶん":1,"わがたひろゆき":1,"わーるどとりがー":1,"わふなっつ":1,"わいどれんず":1,"わくせいさんぼう":1,"わちがい":1,"わーるどげーむず":1,"わかばいろ":1,"わきかいどう":1,"わけなく":1,"わけぎ":1,"わいるどあだぷたー":1,"わたなべとしみち":1,"わざわいてんじてふくとなす":1,"われらが":1,"わたしのおとちゃばこ":1,"わーどばすけっと":1,"わきげぴー":1,"わたなべひさのぶ":1,"わいどいんたーねっと":1,"わかやましえき":1,"われたりんご":1,"わんさか":1,"わいふすとっぷ":1,"わかみやちょう":1,"わたふぇい":1,"わかつきちなつ":1,"わがつまさかえ":1,"わさびねこ":1,"わたなべまさし":1,"わたなべしげお":1,"わんみ":1,"わわわ":1,"わさび":1,"わぴーきゃらくたーず":1,"わしょくかいき":1,"わだけいさく":1,"わどく":1,"わふぅ":1,"わかみ":1,"わらじ":1,"わりまえかんじょう":1,"わせださが":1,"わごとう":1,"わらい":1,"わかやまきいちろう":1,"わりびきがきく":1,"わおびっち":1,"わんしょっときゃのん":1,"わかたかふぃーばー":1,"わたつきのすぺるかーど":1,"わたくしあめ":1,"わにす":1,"わんがんせんそうしょうこうぐん":1,"わんだーしている":1,"わっちゃ":1,"わかばやしたろう":1,"わっこわぁひょうじょぱきっ":1,"わたりひとつぎ":1,"わだえき":1,"わんまいるうえあ":1,"わーるどくらぶちゃれんじ":1,"わらえるはなしばくしょうふっきんほうかいねたけいわらえるはなしをまとめました":1,"わぷてぃあ":1,"わたしのにゅうりんさんてんいちよん":1,"わかやましそのべ":1,"わかぎえふ":1,"わかぱい":1,"わーむ":1,"わーにんぐだらいあすさん":1,"わーくすてーしょんしきべつし":1,"わせだだいがくこうとうがくいんちゅうがくぶ":1,"わだけいいち":1,"わたしはそうぞうする":1,"わろんご":1,"わしのみやちゅうおう":1,"わいすまんせつ":1,"わーくまん":1,"わりざ":1,"わだちきよお":1,"わたしとかれとおおきなとしょかん":1,"わっついん":1,"わけちょう":1,"わかくさいろ":1,"わたしもまた":1,"わかきちょうきた":1,"わたりいた":1,"わかやまけんちじせんきょ":1,"わいんどあっぷ":1,"わかさたかはま":1,"わふくみ":1,"わんこいんべんとう":1,"わんたいむぱっど":1,"わけうり":1,"わきめ":1,"わいずかうんせらー":1,"われひと":1,"わかばだいけんしゃく":1,"わかやまけんけいさつ":1,"わたなべしずこ":1,"われがねのようなこえ":1,"わるいやつら":1,"わーきんぐぷあ":1,"わたそん":1,"わかってもらえなくてもいい":1,"わんにゅう":1,"わかばやしまなぶ":1,"わんわんきゃっち":1,"わたなべばんび":1,"わたなべかつや":1,"わかばやしひさや":1,"わいえいちてぃーえむえる":1,"わはー":1,"わにざめ":1,"わかまつまち":1,"わずかなじかんをみつけて":1,"わみこと":1,"わっさむ":1,"わかやまちほうきしょうだい":1,"わかざくら":1,"わんじぇさんけいおんがくだん":1,"わかなあおい":1,"わっとまん":1,"わせだみなみちょう":1,"わいわいかーど":1,"わかばだいひがし":1,"わへいせんしぶんどっと":1,"わいねふ":1,"わっしゃー":1,"わくわくげんしりょくらんど":1,"わなびーあどりーむめいかー":1,"わるげに":1,"わかさ":1,"わせだだいがくまにふぇすとけんきゅうじょ":1,"わかゆ":1,"わだまち":1,"わんしちゅえーしょん":1,"わえいごりんしゅうせい":1,"わいびーしー":1,"わーくふぇあ":1,"わいんさんち":1,"わたしょのははおや":1,"わこーちかこ":1,"わいが":1,"わたなべかこ":1,"わけありしょうひん":1,"わろたそくほう":1,"わきさかまゆ":1,"わんだーうぉーかー":1,"わいたけれ":1,"わんつーぎゃんご":1,"わらいかわせみ":1,"わーむほーる":1,"わせいようご":1,"わたっこ":1,"わらける":1,"わけまち":1,"わくがい":1,"わたなべなおよし":1,"わたさん":1,"わかざむらい":1,"わいるどすとろべりー":1,"わにお":1,"わろすこんぼ":1,"われわれのじょうかいではじゅくじょです":1,"わいえむぴー":1,"わたなべばくと":1,"わたなべいっちょう":1,"わかばやしひろみち":1,"わたなべあいり":1,"わさだ":1,"わがしのひ":1,"わんそくるい":1,"わたべごうた":1,"わかみやさんた":1,"わーるどべーすぼーるくらしっく":1,"わかたけしゅうじ":1,"わふねこ":1,"わけめのぷーさん":1,"わたなべのぶこ":1,"わーるどぶろがーきょうかい":1,"わーぷろけんてい":1,"わごむのせんたんってどこ":1,"わたなべしんとしっくすじょーず":1,"わんまん":1,"わだでん":1,"わーるどぐらんぷりすいえい":1,"わっさむちょう":1,"わすぷきゅう":1,"わかれじ":1,"わーるどおーくしょん":1,"わかむらぎけん":1,"わんぽいんとりりーふ":1,"わこつ":1,"わのなのこくおうのいん":1,"わーくぱっど":1,"わんだほ":1,"わいやーしぇるふ":1,"わんあっぷみゅーじっく":1,"わたくしのりれきしょ":1,"わたなべたくや":1,"わんだりんぐびじたー":1,"わんらぶ":1,"わたしのなかのぎんが":1,"わずらい":1,"わらきあ":1,"わかっててもごろし":1,"わんぱくずもう":1,"わらわら":1,"わき":1,"わおん":1,"わんぱたーん":1,"わぁたん":1,"わらざいく":1,"わたらいぐん":1,"わかすぎかなた":1,"わあわあ":1,"わたなべみゆ":1,"わくわくあっがいらんど":1,"わたしはかごめ":1,"わかみやりな":1,"わかまる":1,"わんおあえいと":1,"わをむすぶ":1,"わしんとんだいがく":1,"わたしあて":1,"わけえき":1,"わだあつし":1,"わてらす":1,"わかまつかねしげ":1,"わたなべみずお":1,"わせじょ":1,"わだごろう":1,"わかげ":1,"わいぱ":1,"わふうとうほうあれんじしりーず":1,"わかりあう":1,"わたなべちょうすけ":1,"わかれさせる":1,"わかどりじだいなると":1,"わぐりたかし":1,"わのなこく":1,"わりおこうざん":1,"わんだりんぐすたー":1,"わしのはどうきゅうはひゃくはちしきまであるぞ":1,"わかさゆえのあやまり":1,"わらじむしぴー":1,"わかやまとらいあんず":1,"わきのけいぶん":1,"わだやま":1,"わかりやすいむりげー":1,"わだつみきよし":1,"わいえふにじゅうさん":1,"わたなべいずみ":1,"わたなべのりつぐ":1,"わいさんさんぶさく":1,"わかいあん":1,"わいるどわんだー":1,"わいえむしーけー":1,"わかいこづえみどり":1,"わかさありた":1,"わざわい":1,"わいじーだぶりゅー":1,"われがち":1,"わるきゅーれのきこう":1,"わりびきかかくせいさく":1,"わるく":1,"わかしゅ":1,"わいばーん":1,"わそうぼん":1,"わしきたきょうた":1,"わーるどわいどうぇぶ":1,"わくらばながれて":1,"わらいのだいがく":1,"わたらせおんせん":1,"わけがわからない":1,"わしばな":1,"わくじろう":1,"わーるどほわいとうぉーるふーうぇあ":1,"わたぬきまさあき":1,"わくおわーる":1,"わいあーるきゅうじゅうきゅう":1,"わきみさききすいよくじょう":1,"わそうぶんかたいしょう":1,"わかさわだ":1,"わんおぶぜむ":1,"わたまきさんぴー":1,"わーくとりつけだい":1,"わいきょうしぇんしょうじん":1,"わいるどぼると":1,"わんきょく":1,"わたあぶら":1,"わーでぃんぐ":1,"わるふぁすつーる":1,"わたなべしん":1,"わきこ":1,"わかやまけんだいいっく":1,"われやすい":1,"わにわにぱにっく":1,"わりあてる":1,"わなしろじょあんな":1,"わりつけたいしょうたい":1,"わたしこーめい":1,"わるのりぷろじぇくと":1,"われにめしなし":1,"わいるどちゃれんじゃー":1,"わかれ":1,"わいしょうわくせい":1,"わなく":1,"わだよしひろ":1,"わからずや":1,"わたなべれん":1,"わたしがふしぎ":1,"わーくえりあ":1,"わかりやすい":1,"わだあつむ":1,"わんずふゅーちゃー":1,"わっほいむすめ":1,"わかやまけんえいきみいでらやきゅうじょう":1,"わたしはこくはくする":1,"わかさおばまかんこうきょうかい":1,"わっほわっほ":1,"わずらわしい":1,"わざわいする":1,"わたなべかずお":1,"わーるどふぉとぷれす":1,"わらうかどにはふくきたる":1,"わきおこる":1,"わかみやひろあき":1,"わきが":1,"わかなえいろ":1,"わくせいけい":1,"わらういぬのせいかつ":1,"わびじん":1,"わんちょぺ":1,"わたなべげきさぶろう":1,"わたなべけあき":1,"わーくらいふばらんす":1,"わかもののすべて":1,"わんちゅく":1,"わめきちらす":1,"わっぱに":1,"わたしのみたそうかがっかいのさいしょにでてくるでんしゃ":1,"わにいまじゅく":1,"わたなべたろう":1,"わんちょ":1,"わっするたっち":1,"わせだつるまきちょう":1,"わぬし":1,"わかみず":1,"わらぶとん":1,"わいんでぃんぐ":1,"わらじむし":1,"わいは":1,"わんつーすりーのひ":1,"わいふ":1,"わだえいさく":1,"わっくんあっとかくれろんじゃ":1,"わらべうた":1,"わたなべけいすけ":1,"わたしおんなだけど":1,"わーぷあんどわーぷ":1,"わいずまーと":1,"わんないきぬほ":1,"わいえふあっとまーくきんよう":1,"わたべゆういちろう":1,"わたなべせいさくしょ":1,"わかたけひこのみこと":1,"わたしのきもち":1,"わかやまちほうけんさつちょう":1,"わかりあうきはあるのか":1,"わかまつせん":1,"わたりかな":1,"わかごますてーくす":1,"わんすたー":1,"わたしとわるつを":1}